Workbook

Sheet Biomarker_Disease
A1: BiomarkerID | B1: Biomarker_Name | C1: Diseasename | D1: ICD11 | E1: ICD10 | F1: ICD9
A2: BM003549 | B2: Neutrophil gelatinase-associated lipocalin (LCN2) | C2: Smallpox | D2: ICD-11: 1E70 | E2: ICD-10: B03 | F2: .
A3: BM002188 | B3: Monocyte chemoattractantprotein-1 (MCP-1) | C3: Amyotrophic lateral sclerosis | D3: ICD-11: 8B60.0 | E3: . | F3: ICD-9: 335.2
A4: BM001695 | B4: HLA class I histocompatibility antigen, B-8 alpha chain (HLA-B) | C4: Myasthenia gravis | D4: ICD-11: 8C6Y | E4: ICD-10: G70.0 | F4: ICD-9: 358
A5: BM000711 | B5: Muscle-specific kinase (MuSK) antibody | C5: Myasthenia gravis | D5: ICD-11: 8C6Y | E5: ICD-10: G70.0 | F5: ICD-9: 358
A6: BM002220 | B6: Muscle-specific kinase (MuSK) antibody | C6: Myasthenia gravis | D6: ICD-11: 8C6Y | E6: ICD-10: G70.0 | F6: ICD-9: 358
A7: BM002933 | B7: Vascular cell adhesion molecule (sVCAM) | C7: Cardiovascular disease | D7: ICD-11: BA00-BE2Z | E7: ICD-10: I00-I99 | F7: .
A8: BM002691 | B8: Sodium/myo-inositol cotransporter (SLC5A3) | C8: Coronary artery disease | D8: ICD-11: BA80 | E8: ICD-10: I25.1, I25.4 | F8: .
A9: BM002750 | B9: Transforming growth factor b (TGF-b) | C9: Asthma | D9: ICD-11: CA23 | E9: ICD-10: J45, J45.8 | F9: ICD-9: 493
A10: BM001941 | B10: Keratin, type II cytoskeletal 1 (KRT1) | C10: Psoriasis vulgaris | D10: ICD-11: EA90 | E10: . | F10: ICD-9: 696
A11: BM001696 | B11: HLA class I histocompatibility antigen, Cw-6 alpha chain (HLA-C) | C11: Psoriasis vulgaris | D11: ICD-11: EA90 | E11: . | F11: ICD-9: 696
A12: BM000396 | B12: HLA class II histocompatibility antigen, DRB1-12 beta chain (HLA-DRB1) | C12: Rheumatoid arthritis | D12: ICD-11: FA20 | E12: . | F12: .
... A2513: BM003018 | B2513: Zinc finger protein ZPR1 (ZPR1) | C2513: Coronary artery disease | D2513: ICD-11: BA80 | E2513: ICD-10: I25.1, I25.4 | F2513: .

Sheet Biomarker_Disease (2)
A1: BiomarkerID | B1: Biomarker_Name | C1: Diseasename | D1: ICD11 | E1: ICD10 | F1: ICD9
A2: BM003549 | B2: Neutrophil gelatinase-associated lipocalin (LCN2) | C2: Smallpox | D2: ICD-11: 1E70 | E2: ICD-10: B03 | F2: .
A3: BM002188 | B3: Monocyte chemoattractantprotein-1 (MCP-1) | C3: Amyotrophic lateral sclerosis | D3: ICD-11: 8B60.0 | E3: . | F3: ICD-9: 335.2
A4: BM001695 | B4: HLA class I histocompatibility antigen, B-8 alpha chain (HLA-B) | C4: Myasthenia gravis | D4: ICD-11: 8C6Y | E4: ICD-10: G70.0 | F4: ICD-9: 358
A5: BM000711 | B5: Muscle-specific kinase (MuSK) antibody | C5: Myasthenia gravis | D5: ICD-11: 8C6Y | E5: ICD-10: G70.0 | F5: ICD-9: 358
A6: BM002220 | B6: Muscle-specific kinase (MuSK) antibody | C6: Myasthenia gravis | D6: ICD-11: 8C6Y | E6: ICD-10: G70.0 | F6: ICD-9: 358
A7: BM002933 | B7: Vascular cell adhesion molecule (sVCAM) | C7: Cardiovascular disease | D7: ICD-11: BA00-BE2Z | E7: ICD-10: I00-I99 | F7: .
A8: BM002691 | B8: Sodium/myo-inositol cotransporter (SLC5A3) | C8: Coronary artery disease | D8: ICD-11: BA80 | E8: ICD-10: I25.1, I25.4 | F8: .
A9: BM002750 | B9: Transforming growth factor b (TGF-b) | C9: Asthma | D9: ICD-11: CA23 | E9: ICD-10: J45, J45.8 | F9: ICD-9: 493
A10: BM001941 | B10: Keratin, type II cytoskeletal 1 (KRT1) | C10: Psoriasis vulgaris | D10: ICD-11: EA90 | E10: . | F10: ICD-9: 696
A11: BM001696 | B11: HLA class I histocompatibility antigen, Cw-6 alpha chain (HLA-C) | C11: Psoriasis vulgaris | D11: ICD-11: EA90 | E11: . | F11: ICD-9: 696
A12: BM000396 | B12: HLA class II histocompatibility antigen, DRB1-12 beta chain (HLA-DRB1) | C12: Rheumatoid arthritis | D12: ICD-11: FA20 | E12: . | F12: .
... A2513: BM003018 | B2513: Zinc finger protein ZPR1 (ZPR1) | C2513: Coronary artery disease | D2513: ICD-11: BA80 | E2513: ICD-10: I25.1, I25.4 | F2513: .

Sheet Sheet2
A1: BiomarkerID | B1: Biomarker_Name | C1: Diseasename | D1: ICD11 | E1: ICD10 | F1: ICD9
A2: BM002860 | B2: Globoside alpha-1,3-N-acetylgalactosaminyltransferase 1 (GBGT1) | C2: Inflammation | D2: ICD-11: 1A00-CA43.1 | E2: . | F2: .
A3: BM002862 | B3: Globoside alpha-1,3-N-acetylgalactosaminyltransferase 1 (GBGT1) | C3: Inflammation | D3: ICD-11: 1A00-CA43.1 | E3: . | F3: .
A4: BM002868 | B4: Globoside alpha-1,3-N-acetylgalactosaminyltransferase 1 (GBGT1) | C4: Inflammation | D4: ICD-11: 1A00-CA43.1 | E4: . | F4: .
A5: BM002870 | B5: Globoside alpha-1,3-N-acetylgalactosaminyltransferase 1 (GBGT1) | C5: Inflammation | D5: ICD-11: 1A00-CA43.1 | E5: . | F5: .
A6: BM001759 | B6: Interleukin-1 family member 10 (IL1F10) | C6: Inflammation | D6: ICD-11: 1A00-CA43.1 | E6: . | F6: .
A7: BM002681 | B7: Lymphocyte adaptor protein LNK | C7: Inflammation | D7: ICD-11: 1A00-CA43.1 | E7: . | F7: .
A8: BM002346 | B8: Nuclear factor of k light polypeptide gene enhancer in B-cells inhibitor | C8: Inflammation | D8: ICD-11: 1A00-CA43.1 | E8: . | F8: .
A9: BM002551 | B9: Poly(A) binding protein | C9: Inflammation | D9: ICD-11: 1A00-CA43.1 | E9: . | F9: .
A10: BM002713 | B10: P-selectin | C10: Inflammation | D10: ICD-11: 1A00-CA43.1 | E10: . | F10: .
A11: BM000031 | B11: Alpha-fetoprotein | C11: Hepatocellular carcinoma | D11: ICD-11: 2C12.02 | E11: ICD-10: C22.0 | F11: ICD-9: 155
A12: BM000698 | B12: a-2 macroglobulin, haptoglobin, total bilirubin, g-glutamyl transferase, ALT, AS T, total cholesterol, TG, fasting blood glucose. | C12: Non-alcoholic steatohepatitis | D12: ICD-11: DB92.1 | E12: ICD-10: K75.8 | F12: ICD-9: 571.8
... A55: BM002808 | B55: Tumor necrosis factor (TNF) | C55: Non-alcoholic steatohepatitis | D55: ICD-11: DB92.1 | E55: ICD-10: K75.8 | F55: ICD-9: 571.8

Sheet Class
A1: Type | B1: Biomarker_ID | C1: Normal Range | D1: Clinical Significance | E1: Description
A2: Predictive Biomarkers | B2: Liver Injury Markers | E2: Liver injury markers are biochemical, molecular, and histopathological indicators used to assess hepatocellular damage, cholestasis, liver function, inflammation, fibrosis, and regeneration.
B5: Alanine Aminotransferase (ALT) | C5: 7–56 U/L | D5: Most specific marker for liver injury | E5: ALT is an enzyme found in the liver that helps convert proteins into energy for the liver cells. When the liver is damaged, ALT is released into the bloodstream and levels increase. This test is sometimes referred to as SGPT.
B6: Aspartate Aminotransferase (AST) | C6: 10–40 U/L | D6: Liver, heart, muscle injury | E6: AST is an enzyme that helps the body break down amino acids. Like ALT, AST is usually present in blood at low levels. An increase in AST levels may mean liver damage, liver disease or muscle damage. This test is sometimes referred to as SGOT.
B7: Gamma-Glutamyl Transferase (GGT) | C7: 5 to 48 U/L | D7: Liver and biliary tract disease | E7: GGT is an enzyme in the blood. Higher-than-usual levels may mean liver or bile duct damage. This test is nonspecific and may be elevated in conditions other than liver disease.
B8: Alkaline phosphatase (ALP) | C8: Adult Men: 40 to 129 U/L Adult Women: 35 to 104 U/L (with temporary elevations expected during pregnancy) Children and Adolescents: 130 to 500+ U/L, | D8: Liver diseases (specifically bile duct obstruction) and bone disorders | E8: ALP is an enzyme found in the liver and bone and is important for breaking down proteins. Higher-than-usual levels of ALP may mean liver damage or disease, such as a blocked bile duct, or certain bone diseases, as this enzyme is also present in bones.
B9: Bilirubin | C9: Total Bilirubin: 0.1 – 1.2 mg/dL Direct (Conjugated): 0.0 – 0.3 mg/dL Indirect (Unconjugated): 0.2 – 0.8 mg/dL | D9: Liver diseases (like hepatitis or cirrhosis), evaluate blocked bile ducts, and investigate hemolytic anemia | E9: Bilirubin is a substance produced during the breakdown of red blood cells. Bilirubin passes through the liver and is excreted in stool. Higher levels of bilirubin might mean liver damage or disease. At times, conditions such as a blockage of the liver ducts or certain types of anemia also can lead to elevated bilirubin.
B10: Lipid Metabolism Markers | E10: Lipid metabolism markers are blood-based biomarkers used to assess how your body processes fats. They identify risks for cardiovascular disease and metabolic syndrome. Key tests include LDL cholesterol (bad cholesterol), HDL cholesterol (good cholesterol), Triglycerides (stored fat), Total Cholesterol, and advanced markers like Apolipoproteins (ApoB/ApoA-1) and Lp(a). These tests measure the balance of lipids in the blood to help detect dyslipidemia. When these markers are abnormal, it indicates a high risk of plaque building up in your arteries (atherosclerosis).
B13: Total cholesterol | C13: Desirable/Normal: Less than 200 mg/dL Borderline high: 200 to 239 mg/dL High: 240 mg/dL or higher | D13: Cardiovascular risk assessment; high levels drive plaque buildup, increasing the risk of coronary artery disease, heart attacks, and strokes | E13: Total cholesterol measures the complete amount of cholesterol—both "bad" (LDL) and "good" (HDL)—circulating in your blood. Its clinical significance lies in cardiovascular risk assessment; high levels drive plaque buildup, increasing the risk of coronary artery disease, heart attacks, and strokes
B14: LDL-C | C14: Optimal: Less than 100 mg/dLNear/Above Optimal: 100–129 mg/dL Borderline High: 130–159 mg/dL High: 160–189 mg/dL Very High: 190 mg/dL and above | D14: Massive hepatic necrosis | E14: LDL-C stands for low-density lipoprotein cholesterol. Known as "bad" cholesterol, it carries cholesterol to body tissues. Excess LDL-C builds up on artery walls as plaque, raising the risk of heart disease and strokes. Experts recommend keeping levels below 100 milligrams per deciliter (mg/dL).Because cholesterol cannot dissolve in the blood, it must be carried by proteins called lipoproteins. LDL-C represents the specific amount of cholesterol circulating inside these low-density particles. While the body requires some cholesterol to build cells and make hormones, high concentrations of LDL-C can lead to atherosclerosis, a condition where the arteries narrow and harden. If plaque ruptures, it can cause dangerous blood clots, potentially triggering a heart attack or stroke
B15: HDL-C | C15: Low HDL (Increased Risk): < 40 mg/dL (males) or < 50 mg/dL (females) Normal HDL: 40 to 80 mg/dL (males) or 50 to 80 mg/dL (females) High HDL (Optimal Protection): ≥ 60 mg/dL for both men and women | D15: A marker for cardiovascular risk. While low levels indicate a higher risk for atherosclerosis and heart disease, extremely high levels are no longer universally considered protective and can paradoxically indicate inflammation or disease. | E15: HDL-C (High-Density Lipoprotein Cholesterol) is the cholesterol transported by high-density lipoproteins. Often called "good" cholesterol, it acts like a scavenger in the bloodstream, absorbing excess cholesterol and plaque-forming fats and carrying them back to the liver to be safely flushed from the body. Because this process actively clears the arteries, higher levels of HDL-C are linked to a lower risk of heart disease and stroke.
B16: Triglycerides | C16: Normal: Less than 150Less than 1.7 Borderline: High150 to 1991.7 to 2.2 High: 200 to 4992.3 to 5.6 Very High: 500 or higher | D16: Ability to reflect metabolic health and cardiovascular risk; elevated levels (hypertriglyceridemia) are directly linked to the hardening of arteries, metabolic syndrome, and acute pancreatitis | E16: Triglycerides are the most common type of fat in our body. They store excess calories from your diet for energy and are transported through your bloodstream. A normal fasting level is typically less than 150 mg/dL, while levels above 200 mg/dL are considered high. Chemically, a triglyceride is an ester derived from a molecule of glycerol combined with three fatty acid chains (represented generally as RCOOH). They make up most of the fats you eat and are also produced by your liver from excess carbohydrates and calories. After you eat, your body converts any calories it doesn't need to use right away into triglycerides, which are then stored in your fat cells. Between meals, hormones release these triglycerides to provide your body with energy.
B17: Free fatty acids | C17: Adults (≥18 years): 0.00–0.72 mmol/L Females: Typically 0.1–0.45 mmol/L Males: Typically 0.1–0.60 mmol/L | D17: Primary indicator of metabolic stress. High concentrations are directly linked to insulin resistance, Type 2 diabetes, obesity, and cardiovascular disease | E17: Free fatty acids (FFAs) are unattached organic compounds found in lipids and fats. Structurally, they consist of a hydrocarbon chain ending in a carboxylic acid group (-COOH). They serve as vital energy substrates, metabolic regulators, and building blocks for cellular membranes, and circulate in the bloodstream bound to albumin.
B18: Glucose/Insulin Resistance Markers | C18: Normal: Below 100 mg/dL (5.6 mmol/L) Prediabetes: 100 to 125 mg/dL (5.6 to 6.9 mmol/L) Diabetes: 126 mg/dL (7.0 mmol/L) or higher (confirmed by two separate tests) | E18: Insulin resistance (IR) markers help determine how effectively your body uses insulin. Key indicators include a HOMA-IR score (calculated from fasting glucose and fasting insulin), HbA1c, and lipid markers like Triglycerides and HDL. For optimal metabolic health, these levels should fall within specific ranges.
B19: Fasting glucose | C19: Adult: between 70 and 99 mg/dL (3.9 to 5.5 mmol/L) | D19: Primarily used to screen for or diagnose diabetes and prediabetes | E19: Fasting blood sugar measures the amount of glucose (sugar) in your bloodstream after you have not eaten or consumed anything besides water for at least 8 hours. It evaluates your body's baseline ability to regulate blood sugar overnight and is primarily used to screen for prediabetes and diabetes. To ensure accurate results, you should avoid eating and drinking (except water) for 8 to 12 hours before the test. This is typically done overnight, with the blood sample drawn first thing in the morning. Always consult your doctor before the test if you are taking any prescription medications, as some may interfere with your blood sugar levels.
B20: HbA1c | C20: Normal: Below 5.7% Prediabetes: 5.7% to 6.4% Diabetes: 6.5% or higher (on two separate tests) | D20: Primarily used to diagnose type 2 diabetes and prediabetes, and to monitor long-term glycemic control | E20: HbA1c (Hemoglobin A1c) measures your average blood sugar levels over the past two to three months. It checks how much sugar is attached to the oxygen-carrying protein in your red blood cells. It is primarily used to diagnose prediabetes and diabetes, and to monitor long-term blood sugar management.
B21: Insulin | C21: Fasting Insulin: Optimal / Low Risk: < 10 µIU/mL Borderline / Early Resistance: 10 – 15 µIU/mL Elevated / Insulin Resistance: > 15 – 25 µIU/mL Postprandial: 30 minutes after eating: 30 – 230 µIU/mL 1 hour after eating: 18 – 276 µIU/mL 2 hours after eating: < 16 to 166 µIU/mL 3+ hours after eating: Returns to normal fasting baseline | D21: Diagnosing and managing metabolic conditions such as diabetes mellitus, insulin resistance, and hypoglycemia | E21: Insulin is a vital peptide hormone produced by the pancreas that regulates blood sugar by allowing cells to absorb glucose from the bloodstream for energy. When this system fails, it leads to conditions like diabetes. Sugar Regulation: When you eat, carbohydrates break down into glucose, entering the bloodstream and raising blood sugar. This triggers the pancreas to release insulin. Energy Delivery: Insulin acts like a "key" that unlocks cell walls in muscles, fat, and the liver, allowing glucose to enter and fuel the body. Storage: Extra glucose is converted into glycogen and stored in the liver and muscles for later use.
B22: HOMA-IR | C22: Optimal insulin sensitivity: Below 1.0 Normal / healthy range: 1.0 to 2.5 Suggests significant insulin resistance: Above 2.5 | D22: A vital blood test used to calculate how effectively your body uses insulin | E22: HOMA-IR (Homeostatic Model Assessment of Insulin Resistance) measures how efficiently your body uses insulin. Calculated using fasting blood glucose and insulin levels, the test evaluates your metabolic health and helps assess your risk for developing prediabetes, type 2 diabetes, and cardiovascular conditions. Early Detection: It identifies insulin resistance years before blood sugar levels rise enough to trigger a type 2 diabetes diagnosis. Evaluating Metabolic Risks: High scores indicate an increased risk for metabolic syndrome, prediabetes, cardiovascular disease, fatty liver, and polycystic ovary syndrome (PCOS). Monitoring Treatment: It allows doctors and patients to track how well lifestyle changes (like diet and weight loss) or medications are improving the body's insulin sensitivity
B23: Adiponectin | C23: Men: 4 to 26 μg/mL Women: 5 to 37 μg/mL | D23: A biomarker for metabolic and cardiovascular disorders | E23: Adiponectin is an abundant protein hormone and adipokine secreted primarily by adipose tissue. It governs energy homeostasis by increasing insulin sensitivity, reducing hepatic glucose production, and promoting fatty acid oxidation. It also exerts potent anti-inflammatory effects. Metabolic Regulation: It enhances cells' responsiveness to insulin, lowering blood sugar and protecting against type 2 diabetes. Cardiovascular Protection: It has anti-atherogenic properties, reducing vascular inflammation and preventing plaque buildup in arteries. Inverse Correlation with Obesity: Serum adiponectin levels are surprisingly lower in obese individuals and those with metabolic syndrome, despite it being a fat-derived hormone. Structural Forms: It is a 244-amino-acid polypeptide that circulates in multimeric species, with high-molecular-weight (HMW) forms being the most biologically active.
B24: Inflammatory Markers | E24: Inflammation markers are blood tests that measure proteins or cell changes indicating inflammation in your body. The most common markers are C-reactive protein (CRP) and Erythrocyte Sedimentation Rate (ESR), which point to an active inflammatory process without identifying its specific root cause.Healthcare providers rely on these markers to detect infections, manage autoimmune diseases (like arthritis), and track the severity of chronic conditions
B25: TNF-α | C25: 0 to 8.1 pg/mL | D25: A primary driver of autoimmune diseases and as a complex biomarker in cancer progression, infection response, and paraneoplastic cachexia | E25: TNF-α (Tumor Necrosis Factor alpha) is a primary immune system cytokine that regulates inflammation and immune cell communication. Released primarily by active macrophages during infection or injury, it triggers localized swelling, fever, and cell death to help the body fight off pathogens and tumors.
B26: IL-6 | C26: 0 and 5 pg/mL | D26: A primary driver of the acute-phase response, making it a critical biomarker for infections, autoimmune disorders, and chronic inflammation | E26: IL-6 (Interleukin-6) is a type of small signaling protein called a cytokine. It plays a critical role in your body's immune system, acting as a conductor for inflammation and the body's defense response to infections, trauma, and tissue injuries. Immune Response: Secreted by white blood cells (like macrophages and T-cells), IL-6 alerts the immune system to pathogens and helps B-cells mature into antibody-producing cells. Triggering Fever: IL-6 acts as a pyrogen. It signals the brain to raise your body temperature when fighting off an infection. Acute Phase: It travels to the liver to stimulate the production of acute-phase proteins (like C-reactive protein or CRP), which are common markers of inflammation
B27: IL-1β | C27: <3.9 pg/mL and 11.7 pg/mL | D27: A gatekeeper of inflammation; excessive or chronic signaling drives multiple autoinflammatory, autoimmune, and cardiovascular diseases | E27: IL-1β (Interleukin-1 beta) is a potent pro-inflammatory cytokine and "endogenous pyrogen" produced by activated immune cells like macrophages. It mediates the body's innate and adaptive immune responses, drives the inflammatory pain pathway, and is responsible for inducing fever by altering the brain's temperature-control centers. Unlike most proteins, IL-1β requires a tight, two-step security system before it can become active: Priming: Inflammatory signals prompt immune cells to synthesize the inactive precursor, pro-IL-1β. Activation: Danger signals activate a specialized protein complex known as the inflammasome. This triggers the enzyme caspase-1, which cleaves the inactive precursor into the mature, biologically active IL-1β cytokine
B28: MCP-1 | C28: Between 150 and 350 pg/mL | D28: A key mediator of inflammation, driving the migration and infiltration of monocytes and macrophages into tissues | E28: Monocyte chemoattractant protein-1 (MCP-1), also known as CCL2, is a key inflammatory cytokine that directs immune cells—primarily monocytes and macrophages—to sites of injury and infection. By binding to the specific receptor CCR2, it triggers immune responses and is often measured as a biomarker for systemic inflammation. Mechanism: It induces chemotaxis (directed cell migration) by activating G-protein-coupled receptors.Structure: It is a small 8.6 kDa protein comprised of 76 amino acids, belonging to the CC chemokine family. Cellular Source: It is secreted by a variety of cells, including endothelial, epithelial, smooth muscle, and immune cells, in response to triggers like interleukins or tissue stress
B29: High-sensitivity CRP (hs-CRP) | C29: Less than 1.0 mg/L | D29: Cardiovascular disease (CVD) risk assessment | E29: A high-sensitivity C-reactive protein (hs-CRP) test is a highly precise blood test that measures minute, baseline levels of CRP—a protein produced by the liver in response to inflammation. Unlike standard CRP tests that detect high inflammation (e.g., from infections or severe trauma), hs-CRP identifies subtle, low-grade inflammation. Elevated levels of hs-CRP serve as an independent marker to assess an individual's risk for cardiovascular events like heart attacks and strokes. It is also closely linked to chronic conditions such as obesity, metabolic syndrome, and type 2 diabetes
B30: Fibrosis Markers | E30: Fibrosis markers are clinical tests that measure extracellular matrix (ECM) remodeling, cellular activity, and scarring in tissues. They range from simple blood panels to specialized genetic tests and imaging techniques used for diagnosis, prognosis, and monitoring treatment efficacy. Liver fibrosis staging relies heavily on non-invasive blood scores and specialized algorithms: FIB-4 Index: A mathematical formula using age, AST, ALT, and platelet count. It is commonly used as an initial screening tool. Enhanced Liver Fibrosis (ELF) Test: A proprietary blood panel that measures hyaluronic acid (HA), procollagen III amino-terminal peptide (PIIINP), and tissue inhibitor of metalloproteinase 1 (TIMP-1). FibroTest / FibroMeter: Algorithms integrating direct markers (like α₂-macroglobulin) and indirect markers (such as bilirubin, GGT, and prothrombin time) to assess liver scarring. Direct ECM Markers: Includes type IV collagen, laminin, and YKL-40, which actively track fibrogenesis
B31: Hyaluronic acid (HA) | C31: 0 to 75 ng/mL | D31: Vital for tissue hydration, lubrication, and cellular signaling | E31: Hyaluronic acid (HA) is a natural, clear, gooey polysaccharide produced by the human body. Acting as a powerful humectant, it can hold up to 1,000 times its weight in water. It is primarily concentrated in the skin, eyes, and joints to provide essential lubrication, structural support, and moisture
B32: PIIINP | C32: Adults (general): 1.7 – 4.2 μ g/L or 2.3 – 6.4 μ g/L | D32: A critical serum biomarker used to assess ongoing fibrosis (tissue scarring) and extracellular matrix remodeling in the body | E32: PIIINP stands for Procollagen Type III Amino Terminal Propeptide. It is a protein fragment released into the bloodstream when the body synthesizes collagen type III, which is a major building block of connective tissues in the skin, lungs, liver, and blood vessels. Because it indicates active connective tissue turnover and scarring, measuring PIIINP levels in the serum provides a reliable, non-invasive biomarker for evaluating several important clinical conditions: Monitoring Liver Fibrosis & Cirrhosis: The most common use for the PIIINP test is to monitor for liver toxicity in patients taking the medication Methotrexate (often prescribed for severe psoriasis). Elevated levels warn that the liver is at risk of developing scar tissue. Assessing Systemic Sclerosis: It is widely used to monitor disease activity and organ tissue remodeling in autoimmune conditions like scleroderma. Indicating Cardiovascular Risk: Elevated PIIINP levels can point toward increased arterial stiffness and preclinical cardiovascular or vascular remodeling. Detecting Inflammatory Conditions: High values can also be observed in patients suffering from inflammatory diseases like pulmonary fibrosis, certain types of arthritis, and following major bone fractures. Understanding your PIIINP levels can help doctors track disease progression and liver health without always needing an invasive liver biopsy.
B33: TIMP-1 | C33: Between 100 ng/mL and 220 ng/mL | D33: A vital biomarker in oncology and fibrotic diseases | E33: TIMP-1 (Tissue Inhibitor of Metalloproteinases 1) is a multifunctional, secreted glycoprotein that regulates extracellular matrix (ECM) remodeling. It functions as a natural inhibitor of Matrix Metalloproteinases (MMPs) a class of enzymes responsible for degrading connective tissues.Key Characteristics and Functions MMP Inhibition: It binds to various MMPs (such as MMP-9) in a 1:1 stoichiometric ratio to block enzyme activity, playing a vital role in processes like wound healing and tissue repair. Cellular Signaling: Beyond inhibiting proteases, TIMP-1 acts as a cytokine and growth factor. By interacting with cell-surface receptors like CD63 and integrins, it can promote cell proliferation and inhibit apoptosis. Clinical Relevance: Its dysregulation is heavily implicated in tumor progression, metastasis, cardiovascular remodeling, and fibrotic conditions. Protein Structure TIMP-1 is approximately 23 kDa in size and belongs to the larger TIMP gene family. Its structure is characterized by two distinct domains: The N-terminal domain contains the inhibitory activity that interacts directly with the catalytic site of MMPs. The C-terminal domain is essential for forming complexes with pro-enzymes (proMMPs) and interacting with specific cell receptors
B34: Type IV collagen | C34: 3.6 to 6.9 ng/mL | D34: Genetic mutations in its genes (COL4A3, COL4A4, COL4A5) cause inherited kidney diseases like Alport syndrome, while elevated serum levels serve as prognostic biomarkers for aggressive cancers (like pancreatic cancer) and liver fibrosis | E34: Type IV collagen is a specialized, network-forming collagen that acts as the principal structural component of the basement membrane (the supportive layer underlying all epithelial and endothelial cells). Unlike fibrillar collagens, it forms a flexible, [sheet-like lattice](0.5.1, 0.5.2) critical for tissue organization, filtration, and cell signaling. Key Characteristics Unique Structure: It is a heterotrimer typically consisting of two α1-like and one α2-like chains. Unlike other collagens, its central triple-helical domain contains multiple amino acid interruptions, which grant the molecule structural [flexibility and kinks](0.5.1, 0.5.2, 0.5.3). Network Assembly: The C-terminal (NC1) and N-terminal (7S) domains of the molecules do not get cleaved during processing, allowing them to bind head-to-head and laterally to form a dense, woven meshwork. Genetics: There are six distinct α-chains (α1 to α6) that assemble into various tissue-specific networks
B35: YKL-40 | C35: 20 to 150 μ g/L (or ng/mL) | D35: Strong correlation with inflammation, tissue remodeling, and fibrosis | E35: YKL-40, also known as Chitinase-3-like protein 1 (CHI3L1), is a 40-kDa secreted glycoprotein. Encoded by the CHI3L1 gene, it is produced by various cell types, including macrophages, neutrophils, and vascular smooth muscle cells. While its exact biological function is unclear, it acts as a key biomarker for inflammation, tissue remodeling, and extracellular matrix degradation.Because YKL-40 plays a prominent role in both acute and chronic inflammatory pathways, it is studied across a wide range of pathological conditions.
B36: Osteopontin | C36: Between 28.6 ng/mL and 118.8 ng/mL | D36: Elevated OPN levels serve as a biomarker for cancer progression, metastasis, and chronic inflammation | E36: Osteopontin (OPN) is a multifunctional glycoprotein and key extracellular matrix component that plays a critical role in cell adhesion, migration, and immune regulation. Widely distributed throughout the body, it is heavily involved in bone metabolism, wound healing, and inflammatory responses. Key Characteristics and Functions Structure: OPN is a highly acidic phosphoprotein. It is encoded by the SPP1 gene and contains specific domains (such as RGD) that allow it to interact with cell-surface receptors, primarily integrins and CD44. Physiological Roles: It is essential for normal bone remodeling, where it helps anchor bone-resorbing cells (osteoclasts) to the mineral matrix. It also acts as a cytokine to aid in the recruitment of immune cells to sites of injury. Pathology: Because it promotes cell survival and invasion, OPN is heavily implicated in tumor progression and the tumor microenvironment, often serving as a biomarker in cancer research. It is also highly expressed in chronic inflammatory and autoimmune diseases like [rheumatoid arthritis](0.5.6, 0.5.7). Modifications: Its bioactivity is tightly regulated by post-translational modifications, including phosphorylation and glycosylation, as well as cleavage by enzymes like thrombin.
B37: Apoptosis Markers | E37: Apoptosis (programmed cell death) is identified through biochemical and morphological changes across three main phases: signal, effector, and degradation. Key markers include Annexin V (detects phosphatidylserine on the cell surface), activated Caspases, cleaved PARP, and Cytochrome c release.
B38: Cytokeratin-18 (CK18-M30) | C38: Less than 150 U/L | D38: Hepatocyte apoptosis. | E38: Cytokeratin-18 (specifically the M30 fragment) is a prominent biomarker for epithelial apoptosis (programmed cell death). When liver or epithelial cells undergo apoptosis, they cleave the CK-18 protein, releasing the M30 fragment into the bloodstream. It is widely used in hepatology to assess liver injury and disease severity. CK18-M30 is heavily studied as a non-invasive alternative to liver biopsy for detecting and monitoring non-alcoholic steatohepatitis (NASH). Increased hepatocyte apoptosis leads to highly elevated blood levels, allowing clinicians to track liver inflammation and fibrosis.
B39: Cytokeratin-18 (CK18-M65) | C39: < 300 U/L | D39: A non-invasive blood test to assess the severity of liver diseases, such as non-alcoholic steatohepatitis (NASH), alcoholic liver disease, and various epithelial cancers | E39: Cytokeratin-18 (CK18-M65) is a serum biomarker that measures total cell death, encompassing both apoptosis (programmed cell death) and necrosis (uncontrolled cell death). When epithelial cells, particularly in the liver, are damaged, they release full-length CK18 and its cleaved fragments into the bloodstream, making M65 a key diagnostic tool for monitoring liver injury and disease progression.
B40: Oxidative Stress Markers | E40: Oxidative stress markers are measurable molecules that indicate the extent of cell and tissue damage caused by an imbalance between free radicals and antioxidants. They evaluate DNA/RNA damage (e.g., 8-OHdG), lipid peroxidation (e.g., MDA, F₂-isoprostanes), and protein oxidation (e.g., protein carbonyls) using blood or urine tests
B41: Malondialdehyde (MDA) | C41: 1.0 to 3.0 nmol/mL | D41: Systemic oxidative stress | E41: Malondialdehyde (MDA) is a highly reactive, naturally occurring organic compound with the chemical formula CH₂(CHO)₂. It is predominantly generated in the body as an end-product of lipid peroxidation the oxidative degradation of polyunsaturated fatty acids in cell membranes. Because its levels rise proportionally with free radical damage, MDA serves as a widely utilized, reliable biomarker for oxidative stress. Beyond being a passive indicator, MDA's small structure allows it to freely react with primary amines found in proteins, nucleic acids, and lipids. This reactivity leads to the formation of cross-linked "adducts" that can cause protein denaturation and mutagenic DNA damage. Because of these characteristics, elevated MDA levels in biological fluids (such as blood plasma, serum, and urine) are frequently investigated in studies related to inflammation, aging, and various chronic pathologies.
B42: Superoxide dismutase (SOD) | C42: Between 150 and 240 U/mL | D42: Disease pathology, biomarker utility, and targeted pharmacology | E42: Superoxide dismutase (SOD) is a vital antioxidant enzyme that acts as the body's first line of defense against cell damage. It neutralizes toxic superoxide radicals by converting them into oxygen and less harmful hydrogen peroxide. SOD is a metalloprotein that requires metal ions (such as copper, zinc, or manganese) to function. In humans, it exists in three distinct forms tailored to protect different parts of the cell: SOD1 (Copper-Zinc SOD): Found in the cytoplasm of cells. SOD2 (Manganese SOD): Located in the mitochondria. SOD3 (Extracellular SOD): Found in the spaces between cells, protecting tissues and blood vessels.
B43: Glutathione (GSH) | C43: 46.9 - 90.1 mg/dL | D43: Diagnostic value as a marker for oxidative stress | E43: Glutathione (GSH) is a potent endogenous tripeptide composed of three amino acids: glutamate, cysteine, and glycine. Produced naturally in the liver and cells, it serves as the body’s master antioxidant, preventing cellular damage caused by reactive oxygen species (ROS), free radicals, peroxides, and heavy metals. Glutathione is critical for many physiological processes, including:Protection from Oxidative Stress: By donating a hydrogen from its sulfur (thiol) group, GSH neutralizes free radicals. In the process, it converts into an oxidized form known as GSSG. Detoxification: GSH binds to heavy metals and lipophilic waste products, facilitating their excretion via bile or urine. Cellular Functions: It assists in regulating redox homeostasis, DNA synthesis, and enzyme activation, ensuring proper immune function.
B44: Catalase | C44: 2869 ± 1039 u/g of hemoglobin | D44: Bacterial identification and human pathophysiology | E44: Catalase is an essential antioxidant enzyme found in nearly all aerobic organisms. Its primary function is to catalyze the rapid breakdown of toxic hydrogen peroxide (H₂O₂) into harmless water and oxygen: 2H₂O₂ → 2H₂O + O₂ Biological Importance Cellular Defense: By neutralizing hydrogen peroxide, catalase protects cellular components including DNA, proteins, and cell membranes from severe oxidative damage. Clinical & Microbiological Use: The Microbe Notes Catalase Test is a fundamental biochemical assay used in microbiology to differentiate bacteria (e.g., distinguishing catalase-positive Staphylococcus from catalase-negative Streptococcus). Aging: Reduced catalase activity has been linked to the graying of human hair
B45: Emerging Omics Biomarkers | E45: Emerging omics-based liver biomarkers offer non-invasive, highly precise alternatives to traditional liver biopsies and blood panels. By analyzing genetic, protein, and metabolic signatures, these technologies target early detection, staging, and personalized treatment of conditions like non-alcoholic fatty liver disease (NAFLD) and hepatocellular carcinoma (HCC).The most promising emerging omics biomarkers include: MicroRNAs (miRNAs): Non-coding RNAs (like miR-122, miR-21, and miR-29) circulate in the blood and can accurately differentiate between simple fatty liver, steatohepatitis (NASH), and fibrosis. Lipidomics: Profiling specific circulating lipids such as ceramies, diacylglycerols (DAGs), and lysophosphatidylcholines (LPC) provides high diagnostic accuracy for predicting liver inflammation. Metabolomics: Analyzing the metabolome tracks advanced fibrosis and inflammation by identifying changes in key molecules, including specific amino acids and bile acids. Proteomics: Circulating proteins (such as Golgi protein-73 / GP73 and heat shock proteins like Hsp90α) are increasingly validated for the early screening and detection of HCC. Multi-Omics: Integrating genomics, transcriptomics, and proteomics using advanced AI and deep learning models enables a more comprehensive understanding of disease progression and helps identify patient-specific molecular subtypes. Despite their potential, translating these discoveries into routine clinical practice currently faces challenges regarding standardization, analytical validity, and untargeted coverage across diverse populations.
B46: miR-122 | C46: Not Applicable | D46: Highly sensitive biomarker for liver injury, chronic viral hepatitis, and hepatocellular carcinoma (HCC) | E46: miR-122 is the most abundant microRNA in the human liver, critically regulating lipid and cholesterol metabolism. In NAFLD and NASH, hepatic miR-122 levels typically rise during early steatosis but decrease with advancing fibrosis. Conversely, serum/circulating miR-122 spikes, serving as a prominent non-invasive biomarker for liver injury. Here is a breakdown of miR-122’s role in NAFLD/NASH: Lipid and Cholesterol Regulation: miR-122 controls genes responsible for the homeostasis between fatty acid and cholesterol biosynthesis (e.g., HMGCS1, HMGCR). A decline in liver miR-122 promotes the accumulation of intrahepatic fat. Inflammation & Fibrosis Progression: Diminished liver miR-122 levels are associated with increased liver inflammation. It protects against liver damage by repressing pro-inflammatory target genes (like Ccl2), which are known to recruit immune cells to the liver. Diagnostic and Prognostic Biomarker: While the absolute amount of miR-122 in liver tissue drops in severe disease, the amount of miR-122 circulating in the blood sharply rises due to hepatocyte stress and cell membrane leakage. Measuring circulating serum miR-122 often alongside other microRNAs like miR-34a provides a promising, non-invasive method to stage NAFLD and diagnose the progression to NASH
B47: miR-34a | C47: Not Applicable | D47: Metabolic diseases, it is upregulated, aggravating fat accumulation, inflammation, and insulin resistance | E47: MicroRNA-34a (miR-34a) is a critical regulatory RNA that is consistently upregulated in the liver and bloodstream during the progression of NAFLD (Non-Alcoholic Fatty Liver Disease) and NASH (Non-Alcoholic Steatohepatitis). It promotes hepatic lipid accumulation, inflammation, and cellular death, making it a key therapeutic target and biomarker for disease severity. Molecular MechanismsLipid Metabolism: miR-34a promotes fat accumulation by increasing lipid absorption and synthesis while simultaneously inhibiting mitochondrial fatty acid oxidation. It does this by repressing genes like PPARα (which drives fat burning) and HNF4α. Disease Progression: In the transition from simple steatosis (NAFL) to NASH, miR-34a triggers hepatocyte apoptosis (cell death) and exacerbates inflammation
B48: miR-192 | C48: Not Applicable | D48: Hepatocellular carcinoma (HCC), non-alcoholic fatty liver disease (NAFLD), liver fibrosis, and drug-induced liver injury (DILI) | E48: miR-192 is a liver-enriched microRNA that plays a critical role in the pathogenesis of Non-Alcoholic Fatty Liver Disease (NAFLD) and Non-Alcoholic Steatohepatitis (NASH). It is highly regarded for its potential as a non-invasive circulating biomarker for diagnosing disease severity and its promise as a therapeutic target to halt lipid accumulation.1. Mechanisms in NAFLD/NASHmiR-192 controls hepatic lipid metabolism, inflammation, and fibrogenesis through distinct molecular pathways: Lipid Regulation: miR-192 acts protectively against dyslipidemia by inhibiting hepatic triglyceride (TG) synthesis. It directly targets genes like Yy1 (Yin Yang 1) and SCD-1 (stearoyl-CoA desaturase 1). Upregulating miR-192 can alleviate hepatic steatosis, whereas its depletion aggravates fat accumulation. Fibrogenesis: miR-192 is actively involved in modulating hepatic stellate cell (HSC) activity. It acts as a profibrogenic molecule that helps control HSC proliferation, migration, and activation during the progression from simple steatosis to NASH.
B49: FGF21 | C49: Between 50 pg/mL and 300 pg/mL | D49: MAFLD (Metabolic Dysfunction-Associated Fatty Liver Disease) and MASH (Metabolic Dysfunction-Associated Steatohepatitis) | E49: Fibroblast Growth Factor 21 (FGF21) is an endocrine hormone primarily produced by the liver that acts as a central regulator of energy metabolism. In the context of non-alcoholic fatty liver disease (NAFLD) and non-alcoholic steatohepatitis (NASH), FGF21 plays a critical role as a compensatory, defensive regulator against metabolic stress and lipotoxicity. Key Characteristics of FGF21 in NAFLD/NASH Disease Progression: NAFLD ranges from simple fatty liver to NASH, which involves liver inflammation (lobular inflammation), hepatocyte ballooning, and fibrosis. Endogenous Upregulation: In patients with NAFLD, circulating and hepatic levels of FGF21 are significantly elevated. This serves as an initial protective, compensatory mechanism by the body to combat lipid accumulation and endoplasmic reticulum (ER) stress. FGF21 Resistance: Despite elevated levels, the body often develops "FGF21 resistance" in advanced stages of NASH. This insensitivity impairs the body's ability to efficiently oxidize fatty acids, allowing the disease to progress. Therapeutic Potential Because of its metabolic properties, FGF21 analogs and FGF21 receptor agonists have emerged as major therapeutic targets in NASH clinical trials. By mimicking the actions of native FGF21, these emerging drugs aim to resolve steatosis, reverse inflammation, and promote weight loss in NASH patients
B50: Fetuin-A | C50: 400 to 800 μg/mL | D50: Elevated levels act as a biomarker for metabolic liver disease and cardiovascular risk, while dropping levels can signal severe, end-stage liver failure | E50: Fetuin-A is a liver-secreted glycoprotein (hepatokine) that plays a central role in the pathogenesis of Non-Alcoholic Fatty Liver Disease (NAFLD) and Non-Alcoholic Steatohepatitis (NASH). Elevated serum levels of Fetuin-A are closely associated with insulin resistance, liver inflammation, and the progression of fatty liver disease. Key Roles of Fetuin-A in NAFLD/NASH Insulin Resistance: Fetuin-A acts as an endogenous inhibitor of the insulin receptor, preventing insulin from properly signaling in muscle and liver cells, which drives systemic insulin resistance. Inflammation: It binds to Toll-like receptor 4 (TLR4) on immune cells and hepatocytes, promoting the release of pro-inflammatory cytokines that trigger the progression of simple fat accumulation (NAFLD) to dangerous liver inflammation and cell damage (NASH). Ectopic Fat Storage: As an adipogenic factor, it promotes the deposition and storage of fat in the liver.
B51: Fetuin-B | C51: Between 3.5 to 16.0 µg/mL | D51: Non-Alcoholic Fatty Liver Disease (NAFLD), liver steatosis, and type 2 diabetes | E51: Fetuin-B is a hepatokine (liver-secreted protein) whose plasma levels are elevated in humans with Non-Alcoholic Fatty Liver Disease (NAFLD) and Non-Alcoholic Steatohepatitis (NASH, now also known as MASH). It is a key factor linking liver fat accumulation to systemic glucose intolerance and type 2 diabetes. How Fetuin-B Drives Disease ProgressionInsulin Resistance: During hepatic steatosis, hepatocytes over-secrete Fetuin-B into the bloodstream. This protein actively impairs insulin action in peripheral tissues (such as myotubes and hepatocytes), contributing directly to glucose intolerance. Aggravating Steatosis: Experimental studies show that Fetuin-B not only results from fatty liver, but it also aggravates hepatic fat accumulation and suppresses lipid oxidation. Promoting Pyroptosis in NASH: In progressive metabolic steatohepatitis (NASH), elevated Fetuin-B downregulates AdipoR1 (Adiponectin Receptor 1), triggering cell death and the activation of inflammatory pathways (such as the NLRP3/GSDMD inflammasome)
B52: PCSK9 | C52: 170 to 220 ng/mL | D52: Binding to LDL receptors on hepatocytes, leading to their destruction | E52: Proprotein Convertase Subtilisin/Kexin type 9 (PCSK9) is a protein central to cholesterol homeostasis. Its exact relationship with Nonalcoholic Fatty Liver Disease (NAFLD) and Nonalcoholic Steatohepatitis (NASH) now often referred to as MASLD and MASH—remains highly debated, with conflicting preclinical findings showing it can both promote fat accumulation and protect against liver injury. The Role of PCSK9 in the Liver Circulating Levels: In humans, elevated levels of circulating PCSK9 are often positively correlated with greater liver fat accumulation and increased severity of hepatic steatosis. Genetic Insights: Studies of genetic Loss-of-Function (LOF) mutations in humans indicate these mutations are typically not associated with a higher risk of NAFLD, showing normal liver function and confirming that PCSK9 inhibitors are safe for the liver. Preclinical Paradox: While circulating PCSK9 correlates with disease severity, some animal studies suggest that knocking out the Pcsk9 gene entirely can actually exacerbate diet-induced liver injury, endoplasmic reticulum (ER) stress, and steatosis. This implies that PCSK9 plays a complex, stage-dependent regulatory role in liver inflammation and lipid handling.
B53: Leptin | C53: Men (Normal BMI): 0.5 to 12.5 ng/mL Women (Normal BMI): 0.5 to 15.2 ng/mL Higher Adiposity / Obese: 20 to 100+ ng/mL | D53: Regulates lipid metabolism and prevents fatty acid accumulation in the liver | E53: Leptin is a fat-derived hormone that acts as a key regulator of energy homeostasis and lipid metabolism. In the context of Non-Alcoholic Fatty Liver Disease (NAFLD) and its more progressive, inflammatory form, NASH (Non-Alcoholic Steatohepatitis), leptin plays a well-documented dual role. The Dual Role of Leptin in Liver Disease Protective / Anti-Steatotic Effect: In the early, healthy stages of metabolism, leptin limits fat accumulation in the liver. It aids in promoting lipid oxidation and suppressing the creation of new fats (de novo lipogenesis). Pro-inflammatory / Pro-fibrotic Effect: As metabolic dysfunction progresses, obesity frequently leads to high circulating levels of leptin (hyperleptinemia) and decreased sensitivity to it (leptin resistance). Under these persistent conditions, leptin shifts from protective to destructive, actively driving the transition from simple fatty liver to NASH and liver fibrosis.
B54: Resistin | C54: 7 to 22 ng/mL | D54: As a key mediator of inflammation and insulin resistance | E54: Resistin is a pro-inflammatory adipokine (a hormone secreted by adipose tissue) that links obesity and insulin resistance to the pathogenesis and progression of Non-Alcoholic Fatty Liver Disease (NAFLD) and Non-Alcoholic Steatohepatitis (NASH). Key Aspects of Resistin in NAFLD/NASH Cellular Origin: While primarily secreted by fat cells (adipocytes) in rodents, human resistin is predominantly produced by macrophages, monocytes, and hepatic stellate cells. Metabolic Impact: Resistin promotes insulin resistance, specifically by increasing hepatic gluconeogenesis and hindering glucose uptake, which serves as the "first hit" in the progression of hepatic steatosis. Inflammation & Fibrosis: It acts as a pro-inflammatory agent that exacerbates liver cell damage. Hepatic resistin expression significantly increases with the severity of liver necroinflammation and fibrosis, driving NASH pathogenesis. Biomarker Potential: Because resistin is overexpressed in liver cells during NASH, elevated circulating serum resistin levels are often evaluated as a biomarker to assess the risk of disease progression, particularly in patients with Type 2 Diabetes.

Sheet Sheet1
A1: Type | B1: Biomarker_ID | D1: Normal Range | E1: Clinical Significance | F1: Description
A2: Blood & Serum Biomarkers | B2: 1. Liver Injury Biomarkers | C2: =VLOOKUP(B2,Class!B:B,2,FALSE) -> #N/A | F2: Liver injury biomarkers are blood tests measuring enzymes and proteins that leak into the bloodstream when liver cells are damaged or when the liver's function is impaired. They are essential for diagnosing, localizing, and monitoring conditions such as hepatitis, cirrhosis, and drug-induced liver injury (DILI).
B3: Routine Liver Function Tests | C3: =VLOOKUP(B3,Class!B:B,2,FALSE) -> #N/A | F3: Routine Liver Function Tests (LFTs) are a group of blood tests used to measure specific enzymes, proteins, and substances to assess overall liver health, screen for infections like hepatitis, monitor medication side effects, and diagnose or monitor liver diseases. The primary components typically measured in a standard LFT profile include: Alanine Aminotransferase (ALT) and Aspartate Aminotransferase (AST): Enzymes concentrated in liver cells. Elevated levels in the bloodstream indicate liver cell injury or inflammation. Alkaline Phosphatase (ALP): An enzyme found in the liver and bones. High levels can suggest issues with the bile ducts or liver damage. Bilirubin: A waste product produced when red blood cells break down, which the liver is responsible for clearing. Elevated levels can cause jaundice and indicate liver disease or blocked bile ducts. Albumin and Total Protein: Albumin is a vital protein created exclusively by the liver, and total protein measures all the proteins in the blood. Low levels can indicate that the liver is not producing proteins properly or may point to chronic kidney/liver conditions. Gamma-glutamyl Transferase (GGT): An enzyme often added to screen for liver and bile duct stress or damage, particularly from alcohol use. Prothrombin Time (PT): Measures how long your blood takes to clot. Because the liver produces clotting factors, an abnormal PT time can indicate impaired liver function.
B4: Alanine aminotransferase (ALT) | C4: =VLOOKUP(B4,Class!B:B,2,FALSE) -> #REF!
B5: Aspartate aminotransferase (AST) | C5: =VLOOKUP(B5,Class!B:B,2,FALSE) -> #REF!
B6: Gamma-glutamyl transferase (GGT) | C6: =VLOOKUP(B6,Class!B:B,2,FALSE) -> #REF!
B7: Alkaline phosphatase (ALP) | C7: =VLOOKUP(B7,Class!B:B,2,FALSE) -> #REF!
B8: Lactate dehydrogenase (LDH) | C8: =VLOOKUP(B8,Class!B:B,2,FALSE) -> #N/A
B9: Total bilirubin | C9: =VLOOKUP(B9,Class!B:B,2,FALSE) -> #N/A
B10: Direct bilirubin | C10: =VLOOKUP(B10,Class!B:B,2,FALSE) -> #N/A
B11: Indirect bilirubin | C11: =VLOOKUP(B11,Class!B:B,2,FALSE) -> #N/A
B12: Liver Synthetic Function | C12: =VLOOKUP(B12,Class!B:B,2,FALSE) -> #N/A | F12: Liver synthetic function is the organ's ability to produce essential blood proteins, coagulation factors, and biochemical molecules. It is clinically assessed by measuring serum albumin (for chronic capacity) and prothrombin time/INR (for acute capacity). Core Synthetic ProcessesProtein Synthesis: The liver produces roughly 90% of circulating blood proteins, most notably albumin. Albumin maintains intravascular oncotic pressure and transports hormones, fatty acids, and drugs. It also synthesizes carrier proteins like transferrin (for iron transport). Coagulation Factors: The liver is the primary site of synthesis for nearly all clotting factors (e.g., fibrinogen, prothrombin, factors V, VII, IX, and X). It also synthesizes natural anticoagulants like protein C and protein S. Metabolite and Energy Production: The liver continuously synthesizes lipids, cholesterol (to build cell membranes and bile acids), and lipoproteins. During fasting, it synthesizes glucose (gluconeogenesis) and produces ketone bodies as alternative brain fuel. Regulatory Molecules: It creates key hormones and regulatory proteins, such as thrombopoietin (which stimulates platelet production) and angiotensinogen (which regulates blood pressure). Clinical Significance & Testing Because the liver has a large functional reserve, synthetic function typically remains well-preserved until liver disease becomes advanced or chronic (e.g., cirrhosis). Albumin Testing: Albumin has a long circulatory half-life (about 21 days). A low serum level (hypoalbuminemia) indicates long-term, chronic liver impairment or severe malnutrition. PT/INR Testing: The liver's coagulation factors have much shorter half-lives. Prolonged prothrombin time (PT) or an elevated international normalized ratio (INR) serves as a highly sensitive, acute indicator of failing synthetic capacity and elevated bleeding risk.
B13: Albumin | C13: =VLOOKUP(B13,Class!B:B,2,FALSE) -> #N/A
B14: Total protein | C14: =VLOOKUP(B14,Class!B:B,2,FALSE) -> #N/A
B15: Globulin | C15: =VLOOKUP(B15,Class!B:B,2,FALSE) -> #N/A
B16: Albumin/Globulin ratio | C16: =VLOOKUP(B16,Class!B:B,2,FALSE) -> #N/A
B17: Prothrombin time (PT) | C17: =VLOOKUP(B17,Class!B:B,2,FALSE) -> #N/A
B18: International Normalized Ratio (INR) | C18: =VLOOKUP(B18,Class!B:B,2,FALSE) -> #N/A
B19: 2. Metabolic Biomarkers | C19: =VLOOKUP(B19,Class!B:B,2,FALSE) -> #N/A | F19: Metabolic biomarkers are measurable biological indicators such as specific molecules or hormones in blood or urine that reflect how your body processes and utilizes energy. They are crucial for diagnosing metabolic conditions (like diabetes and cardiovascular disease), tracking organ function, and evaluating your overall physiological health. The most critical metabolic biomarkers are often grouped into a standard metabolic panel: Blood Glucose & Insulin: Measures your body's ability to process sugars. Indicators like fasting glucose and HbA1c (average blood sugar over 3 months) identify risks for insulin resistance and type 2 diabetes. Lipid Profile: Tracks fat-based particles in your blood. Key markers include triglycerides, HDL (high-density lipoprotein/"good" cholesterol), and LDL (low-density lipoprotein/"bad" cholesterol) to assess cardiovascular risk. Liver & Kidney Markers: Biomarkers like ALT (alanine aminotransferase) for liver health and BUN/Creatinine for kidney function help catch organ stress or damage early. Inflammatory Markers: Proteins like hs-CRP (high-sensitivity C-reactive protein) indicate chronic, low-grade inflammation, which is often tied to metabolic syndrome
B20: Glucose Metabolism | C20: =VLOOKUP(B20,Class!B:B,2,FALSE) -> #N/A | F20: Glucose metabolism refers to the bodily processes that break down, utilize, and store glucose (sugar) from food. It is the primary way your cells generate energy to keep your body functioning. How the Process Works? Glucose metabolism encompasses a few key, continuous processes to manage energy:Glycolysis: The breakdown of glucose in cells to produce immediate energy in the form of ATP (Adenosine Triphosphate).Glycogenesis: The synthesis and storage of excess glucose as glycogen (primarily in the liver and muscles) for later use.Glycogenolysis: The breakdown of stored glycogen back into glucose when blood sugar is low (like during sleep or fasting).Gluconeogenesis: The synthesis of new glucose from non-carbohydrate sources, such as amino acids, when energy reserves are depleted. The Role of Hormones This intricate process is heavily regulated by hormones released by the pancreas:Insulin: Secreted after a meal to lower blood sugar. It acts as a key, unlocking cell membranes so glucose can enter tissue cells for energy or storage.Glucagon: Secreted during fasting to raise blood sugar. It signals the liver to convert stored glycogen back into glucose. Why It Matters? Glucose is the essential fuel source for nearly all cells, especially the brain and nervous system. When glucose metabolism functions normally, your body maintains a healthy, balanced blood sugar level.Impairments or breakdowns in this system such as insulin resistance, where cells fail to respond effectively to insulin often lead to conditions like prediabetes or type 2 diabetes.
B21: Fasting blood glucose (FBG) | C21: =VLOOKUP(B21,Class!B:B,2,FALSE) -> #N/A
B22: Random blood glucose | C22: =VLOOKUP(B22,Class!B:B,2,FALSE) -> #N/A
B23: Hemoglobin A1c (HbA1c) | C23: =VLOOKUP(B23,Class!B:B,2,FALSE) -> #N/A
B24: Fasting insulin | C24: =VLOOKUP(B24,Class!B:B,2,FALSE) -> #N/A
B25: C-peptide | C25: =VLOOKUP(B25,Class!B:B,2,FALSE) -> #N/A
B26: HOMA-IR | C26: =VLOOKUP(B26,Class!B:B,2,FALSE) -> #REF!
B27: HOMA-β | C27: =VLOOKUP(B27,Class!B:B,2,FALSE) -> #N/A
B28: Lipid Profile | C28: =VLOOKUP(B28,Class!B:B,2,FALSE) -> #N/A | F28: A lipid profile (or lipid panel) is a blood test that measures the amount of cholesterol and other fats in your blood. It is a crucial screening tool used by doctors to assess your cardiovascular health and determine your risk for developing heart disease, blockages in your arteries, or having a stroke. A standard lipid profile typically measures the following specific components: Total Cholesterol: The overall amount of cholesterol circulating in your bloodstream (including both "good" and "bad" types). Optimal Level: Below 200 mg/dL.Low-Density Lipoprotein (LDL) Cholesterol: Often referred to as "bad cholesterol". High levels can build up in the walls of your blood vessels, forming plaque that restricts blood flow and increases the risk of heart attacks. Optimal Level: Below 100 mg/dL. High-Density Lipoprotein (HDL) Cholesterol: Known as "good cholesterol". It actively sweeps excess cholesterol out of your bloodstream and transports it back to the liver to be broken down, offering protection against heart disease. Optimal Level: 60 mg/dL or higher. Triglycerides: A type of fat (lipid) that your body makes from excess calories and the food you eat. They are stored in your fat cells for energy, but high levels are linked to a higher risk of heart disease and insulin resistance. Optimal Level: Below 150 mg/dL. Very Low-Density Lipoprotein (VLDL) Cholesterol: Often calculated based on your triglyceride level. VLDL mainly carries triglycerides in the blood and high levels can also indicate a risk of artery blockages. Optimal Level: Below 30 mg/dL
B29: Total cholesterol | C29: =VLOOKUP(B29,Class!B:B,2,FALSE) -> #REF!
B30: Triglycerides | C30: =VLOOKUP(B30,Class!B:B,2,FALSE) -> #REF!
B31: HDL cholesterol | C31: =VLOOKUP(B31,Class!B:B,2,FALSE) -> #N/A
B32: LDL cholesterol | C32: =VLOOKUP(B32,Class!B:B,2,FALSE) -> #N/A
B33: VLDL cholesterol | C33: =VLOOKUP(B33,Class!B:B,2,FALSE) -> #N/A
B34: Non-HDL cholesterol | C34: =VLOOKUP(B34,Class!B:B,2,FALSE) -> #N/A
B35: Free fatty acids (FFA) | C35: =VLOOKUP(B35,Class!B:B,2,FALSE) -> #N/A
B36: Apolipoprotein A1 | C36: =VLOOKUP(B36,Class!B:B,2,FALSE) -> #N/A
B37: Apolipoprotein B | C37: =VLOOKUP(B37,Class!B:B,2,FALSE) -> #N/A
B38: Lipoprotein(a) | C38: =VLOOKUP(B38,Class!B:B,2,FALSE) -> #N/A
B39: 3. Inflammatory Biomarkers | C39: =VLOOKUP(B39,Class!B:B,2,FALSE) -> #N/A | F39: Inflammatory biomarkers are measurable substances in the body such as proteins, enzymes, and cells that indicate the presence and severity of inflammation. Doctors use blood or stool tests to detect these markers, which helps diagnose infections, autoimmune diseases, and chronic conditions like heart disease or inflammatory bowel disease. Because inflammatory biomarkers are typically non-specific meaning an elevated level signals inflammation but rarely points to a single, exact cause they are usually ordered alongside a thorough physical exam and clinical history. The most common inflammatory biomarkers include: C-Reactive Protein (CRP): Produced by the liver, CRP is the most widely used marker to detect acute inflammation caused by severe infections, tissue damage, or autoimmune flare-ups. A specialized version, hs-CRP (High-Sensitivity CRP), is used to measure low-grade chronic inflammation and assess cardiovascular risk. Erythrocyte Sedimentation Rate (ESR): This test measures how quickly red blood cells settle in a test tube. Inflammatory proteins cause red blood cells to clump and settle faster, signaling ongoing inflammation. Cytokines: These are small signaling proteins (such as Interleukin-6 and TNF-alpha) that regulate immune responses. They are often elevated in severe inflammatory conditions and cancers. Procalcitonin (PCT): This marker is particularly useful for detecting severe bacterial infections and guiding antibiotic therapy, especially in cases of sepsis. Plasma Viscosity (PV): Similar to ESR, this measures the thickness of blood plasma. It is sometimes preferred over ESR because it is not affected by a patient's age or sex. Calprotectin: Frequently measured in stool samples, this protein is a highly reliable biomarker for intestinal inflammation, aiding in the diagnosis and monitoring of Inflammatory Bowel Disease (IBD)
B40: Cytokines | C40: =VLOOKUP(B40,Class!B:B,2,FALSE) -> #N/A | F40: Cytokines are small proteins secreted by cells that act as chemical messengers. They are essential for regulating the immune system, controlling inflammation, and dictating how cells grow and divide. When the body faces an infection or injury, immune and non-immune cells release cytokines to coordinate a targeted defense. Key Types of Cytokines Cytokines are categorized into several major groups based on their structure and function: Interleukins (ILs): Regulate immune and inflammatory responses, often acting as messengers between different white blood cells. Chemokines: Direct immune cells to the specific site of an infection or tissue damage through a process called chemotaxis. Interferons (IFNs): Help defend against viruses by preventing them from multiplying and stimulating other immune cells to fight the infection. Tumor Necrosis Factors (TNFs): Help trigger inflammation and can directly destroy certain types of cells, including cancer cells. Colony-Stimulating Factors (CSFs): Stimulate the bone marrow to produce and differentiate new blood and immune cells. How They Work? Cytokines operate by binding to specific receptors on the surface of target cells. This binding triggers a chain reaction inside the cell that tells it to grow, die, or move. They act in three primary ways: Autocrine: A cell secretes cytokines to signal itself. Paracrine: A cell secretes cytokines to signal nearby, neighboring cells. Endocrine: Cytokines enter the bloodstream to signal distant cells or organs (e.g., triggering a fever in the brain). Medical Relevance! Because they dictate how the body responds to illness, cytokines are heavily studied in medicine. An overreaction of the immune system can cause a dangerous flood of cytokines, known as a cytokine storm, which can damage healthy tissues. Conversely, lab-made versions of cytokines (like Interleukin-2) are used as immunotherapies to treat certain conditions, such as advanced kidney cancer and metastatic melanoma.
B41: Tumor necrosis factor-alpha (TNF-α) | C41: =VLOOKUP(B41,Class!B:B,2,FALSE) -> #N/A
B42: Interleukin-1β (IL-1β) | C42: =VLOOKUP(B42,Class!B:B,2,FALSE) -> #N/A
B43: Interleukin-6 (IL-6) | C43: =VLOOKUP(B43,Class!B:B,2,FALSE) -> #N/A
B44: Interleukin-8 (IL-8) | C44: =VLOOKUP(B44,Class!B:B,2,FALSE) -> #N/A
B45: Interleukin-18 (IL-18) | C45: =VLOOKUP(B45,Class!B:B,2,FALSE) -> #N/A
B46: Interleukin-17 (IL-17) | C46: =VLOOKUP(B46,Class!B:B,2,FALSE) -> #N/A
B47: Chemokines | C47: =VLOOKUP(B47,Class!B:B,2,FALSE) -> #N/A | F47: Chemokines are a family of small, secreted signaling proteins that act as chemoattractants. They direct the movement of white blood cells and other cells through the body by inducing directional migration (chemotaxis) along a chemical gradient.They play crucial roles in maintaining the immune system, mounting inflammatory responses to fight infections, and managing normal tissue growth. Key Characteristics Size & Structure: They are small proteins, roughly 8–10 kilodaltons, defined by specific, conserved cysteine residues. Classification: They are grouped into four main sub-families based on the arrangement of their initial cysteine amino acids: CC, CXC, C, and CX3C. Receptors: Chemokines exert their effects by binding to specific G protein-coupled receptors (GPCRs) on the surface of target cells. Primary Functions Inflammation: They act as alarm signals. When a tissue is injured or infected, cells secrete chemokines to attract immune cells like neutrophils and macrophages to the affected area to fight the pathogen and heal the wound. Homeostasis: Some chemokines are continuously active, managing the regular movement and development of immune cells throughout healthy tissues and organs. Cell Signaling: By binding to their receptors, chemokines trigger intracellular signaling cascades that not only direct cell movement but also promote cell survival and growth. Because of their critical role in cell trafficking, chemokines are also heavily involved in various disease processes, including autoimmune disorders, tumor growth, and viral infections
B48: Monocyte chemoattractant protein-1 (MCP-1/CCL2) | C48: =VLOOKUP(B48,Class!B:B,2,FALSE) -> #N/A
B49: CCL5 (RANTES) | C49: =VLOOKUP(B49,Class!B:B,2,FALSE) -> #N/A
B50: CXCL10 | C50: =VLOOKUP(B50,Class!B:B,2,FALSE) -> #N/A
B51: Acute Phase Proteins | C51: =VLOOKUP(B51,Class!B:B,2,FALSE) -> #N/A | F51: Acute Phase Proteins are blood proteins synthesized by the liver that change in concentration by at least 25% in response to inflammation, infection, or tissue injury. They form a core part of the innate immune response, helping to clear pathogens, neutralize harmful enzymes, and restore bodily homeostasis. These proteins are broadly classified into two main categories: Positive Acute Phase Proteins: Their levels increase in the blood. They actively aid in fighting infection and inflammation. Common examples include: C-Reactive Protein (CRP): Promotes phagocytosis (engulfing of pathogens) and activates the complement system. Fibrinogen: Aids in blood clot formation to limit the spread of infections. Ferritin: Binds and sequesters iron, which deprives invading bacteria of a vital nutrient. Serum Amyloid A (SAA): Helps recruit inflammatory cells to the site of injury or infection. Negative Acute Phase Proteins: Their levels decrease in the blood. The liver reduces the synthesis of these proteins to conserve amino acids and energy, prioritizing the production of positive acute phase proteins. Common examples include albumin and transferrin. The production of these proteins is triggered by immune signaling molecules, primarily cytokines like IL-6, IL-1, and TNF-α. Because their levels shift rapidly, acute phase proteins (especially CRP) are frequently used as clinical biomarkers to detect, diagnose, and monitor the severity of inflammatory diseases and infections
B52: High-sensitivity C-reactive protein (hs-CRP) | C52: =VLOOKUP(B52,Class!B:B,2,FALSE) -> #N/A
B53: Serum amyloid A (SAA) | C53: =VLOOKUP(B53,Class!B:B,2,FALSE) -> #N/A
B54: Ferritin | C54: =VLOOKUP(B54,Class!B:B,2,FALSE) -> #N/A
B55: 4. Fibrosis Biomarkers | C55: =VLOOKUP(B55,Class!B:B,2,FALSE) -> #N/A | F55: Fibrosis biomarkers are measurable biological molecules in blood, tissue, or bodily fluids that indicate the presence and severity of scar tissue (fibrosis) in organs like the liver, lungs, or kidneys. They provide vital, non-invasive alternatives to biopsies for diagnosing and monitoring disease progression. These diagnostic tools are typically categorized into two main types: Direct Biomarkers: These measure the actual turnover of extracellular matrix (ECM) proteins, such as collagens, which are deposited during scarring. Examples include Hyaluronic Acid (HA), Procollagen III Amino-Terminal Peptide (PIIINP), and Tissue Inhibitors of Metalloproteinase-1 (TIMP-1). Tests like the Enhanced Liver Fibrosis (ELF) test combine these direct markers to gauge advanced disease. Indirect Biomarkers: These are calculated scores derived from routine lab tests that reflect organ dysfunction caused by fibrosis. Common examples include the FIB-4 Index (based on age, AST, ALT, and platelets) and the APRI score (based on AST and platelet counts). In addition to liver disease, biomarkers play a crucial role in conditions like Idiopathic Pulmonary Fibrosis (IPF) in the lungs, where proteins such as Periostin and Galectin-3 are used to predict lung function decline
B56: Extracellular Matrix Components | C56: =VLOOKUP(B56,Class!B:B,2,FALSE) -> #N/A | F56: The Extracellular Matrix (ECM) is a dynamic, 3D network of macromolecules (like proteins and polysaccharides) that fills the spaces between cells. It provides crucial structural scaffolding, mechanical support, and biochemical signaling to guide cell growth, migration, and tissue organization.The ECM's primary functional components include: Collagen: The most abundant protein in the ECM. It forms triple-helix fibrils that provide vital tensile strength and structural integrity to tissues like skin, tendons, and bones. Elastin: A highly elastic, cross-linked fibrous protein that allows tissues (such as the lungs and blood vessels) to stretch and recoil back to their original shape. Proteoglycans: Heavily glycosylated proteins that trap water to form a hydrated, gel-like "ground substance". They act as a compression buffer and a reservoir for growth factors. Glycosaminoglycans (GAGs): Long, unbranched chains of polysaccharides (e.g., hyaluronan) that attach to proteoglycans to absorb immense compression forces. Fibronectin & Laminin: Multi-adhesive glycoproteins that physically link the ECM to the cell membrane (via integrins), allowing for vital cell-to-cell communication and migration
B57: Hyaluronic acid (HA) | C57: =VLOOKUP(B57,Class!B:B,2,FALSE) -> #REF!
B58: Type IV collagen | C58: =VLOOKUP(B58,Class!B:B,2,FALSE) -> #REF!
B59: Type III collagen | C59: =VLOOKUP(B59,Class!B:B,2,FALSE) -> #N/A
B60: Laminin | C60: =VLOOKUP(B60,Class!B:B,2,FALSE) -> #N/A
B61: Fibrogenesis Markers | C61: =VLOOKUP(B61,Class!B:B,2,FALSE) -> #N/A | F61: Fibrogenesis markers are clinical indicators that measure the body's active process of laying down fibrous, scar-forming connective tissue (extracellular matrix) in organs, most commonly the liver. They are primarily categorized into Direct (Class I) and Indirect (Class II) markers to assess disease activity and progression. Direct (Class I) Markers: These specifically measure the molecules involved in extracellular matrix (ECM) turnover, such as the synthesis or degradation of collagen. They indicate "what is going on" with the actual fibrogenic process. Common examples include Hyaluronic acid (HA), Procollagen type III N-terminal peptide (PIIINP), and Laminin. Indirect (Class II) Markers: These are routine, empiric laboratory tests that reflect overall organ dysfunction caused by scarring (e.g., liver function) rather than ECM production itself. They help establish the "stage" of fibrosis. Examples include AST/ALT ratios, Platelet counts, Bilirubin, and algorithms like the FIB-4 score and APRI
B62: Procollagen III N-terminal peptide (PIIINP) | C62: =VLOOKUP(B62,Class!B:B,2,FALSE) -> #N/A
B63: Tissue inhibitor of metalloproteinase-1 (TIMP-1) | C63: =VLOOKUP(B63,Class!B:B,2,FALSE) -> #N/A
B64: Matrix metalloproteinase-2 (MMP-2) | C64: =VLOOKUP(B64,Class!B:B,2,FALSE) -> #N/A
B65: Matrix metalloproteinase-9 (MMP-9) | C65: =VLOOKUP(B65,Class!B:B,2,FALSE) -> #N/A
B66: Advanced Fibrosis Markers | C66: =VLOOKUP(B66,Class!B:B,2,FALSE) -> #N/A | F66: Advanced fibrosis markers are non-invasive blood tests and imaging tools used to assess the severity of liver scarring (fibrosis). They eliminate the need for painful liver biopsies by categorizing scarring into stages (usually F0-F4), with stages F3-F4 representing "advanced" fibrosis or cirrhosis. These assessments are broken down into two main categories: 1. Simple Blood Tests (Indirect Markers): These use standard, inexpensive, and widely available lab work to calculate a score based on liver function and systemic changes. FIB-4 Index: Calculates fibrosis risk based on a patient's age, platelet count, AST, and ALT levels. It is highly recommended by medical guidelines to rule out advanced fibrosis. NAFLD Fibrosis Score (NFS): Evaluates six factors: age, body mass index (BMI), platelet count, albumin, AST/ALT ratio, and presence of diabetes/hyperglycemia. APRI (AST to Platelet Ratio Index): Uses AST levels and platelet counts to quickly predict significant fibrosis. 2. Specialized Blood Tests (Direct Markers): These complex panels measure molecules actively involved in the creation or breakdown of scar tissue (fibrogenesis). ELF (Enhanced Liver Fibrosis) Test: Combines measurements of hyaluronic acid (HA), amino-terminal propeptide of type III procollagen (PIIINP), and tissue inhibitor of metalloproteinase 1 (TIMP-1). It is highly accurate in assessing advanced fibrosis across various chronic liver diseases. FibroTest / FibroSure: Measures components like alpha-2-macroglobulin, haptoglobin, total bilirubin, and GGT to gauge fibrosis levels. 3. Imaging Modalities (Elastography): Imaging tests measure the actual physical stiffness of the liver tissue a stiffer liver corresponds to a higher degree of fibrosis. FibroScan (VCTE): Uses specialized ultrasound waves to measure liver stiffness and estimate fat content (CAP scores). Magnetic Resonance Elastography (MRE): Considered the most accurate non-invasive imaging method for mapping fibrosis severity across the entire liver.
B67: YKL-40 (CHI3L1) | C67: =VLOOKUP(B67,Class!B:B,2,FALSE) -> #N/A
B68: Osteopontin (OPN) | C68: =VLOOKUP(B68,Class!B:B,2,FALSE) -> #N/A
B69: Connective tissue growth factor (CTGF) | C69: =VLOOKUP(B69,Class!B:B,2,FALSE) -> #N/A
B70: Transforming growth factor-beta (TGF-β1) | C70: =VLOOKUP(B70,Class!B:B,2,FALSE) -> #N/A
B71: 5. Hepatocyte Apoptosis Biomarkers | C71: =VLOOKUP(B71,Class!B:B,2,FALSE) -> #N/A | F71: Hepatocyte apoptosis biomarkers are indicators used to detect and quantify programmed liver cell death. They are primarily used in non-invasive blood tests to assess the severity of liver diseases such as NASH, viral hepatitis, and alcoholic liver disease without the need for a surgical liver biopsy. Core Biomarkers: Cytokeratin-18 (CK-18): The most widely used circulating biomarker for hepatocyte death. CK-18 is an abundant structural protein in liver cells. During apoptosis, it is cleaved by caspases. ccK18 (Caspase-cleaved CK-18 / M30 fragment): Specifically indicates apoptosis. Elevated levels are detected using the Peviva M30 Apoptosense Assay.Total CK18 / M65: Measures both apoptosis and necrosis (unregulated cell death). It is measured using the Peviva M65 ELISA. M30 : M65 Ratio: A metric used to determine whether the dominant form of cell death in the liver is apoptosis or necrosis.Underlying Pathways & Mechanisms These biomarkers reflect the two main pathways of apoptosis in hepatocytes: Extrinsic Pathway: Triggered when "death ligands" in the blood (such as FasL or TNF-α) bind to death receptors on the surface of the hepatocyte, initiating a chain of cell-death signals. Intrinsic Pathway: Triggered internally by cellular stressors like oxidative stress, endoplasmic reticulum (ER) stress, or mitochondrial dysfunction. This pathway involves the release of proteins like cytochrome c into the cell cytoplasm, activating executioner caspases (e.g., Caspase-3). Clinical SignificanceLiver Fibrosis and Disease Progression: High levels of apoptotic biomarkers correlate with disease severity, liver ballooning, and inflammation.Treatment Monitoring: These markers are highly valuable for tracking how well a patient is responding to therapies or lifestyle changes (e.g., exercise reducing apoptosis in NAFLD)
B72: Cytokeratin Markers | C72: =VLOOKUP(B72,Class!B:B,2,FALSE) -> #N/A | F72: Cytokeratins are structural proteins forming the internal framework (intermediate filaments) of epithelial cells. In diagnostic pathology, these markers are critical for identifying epithelial-derived cancers (carcinomas). Different combinations of cytokeratins (numbered 1-20) are highly specific to particular organs, allowing pathologists to pinpoint the exact origin of a tumor. Why Cytokeratin Markers Are Used? Epithelial Screening: Broad-spectrum markers like AE1/AE3 are used to confirm if a poorly differentiated tumor is a carcinoma rather than a lymphoma or sarcoma. Cancer Differentiation: Specific CKs map to specific tissues. For example, CK5/6 strongly points to squamous cell carcinoma or mesothelioma, while CK7 is useful for distinguishing between ovarian and gastrointestinal carcinomas. Blood-Based Tumor Monitoring: Soluble fragments of cytokeratins (such as CYFRA 21-1 and TPS) are measured in the blood of cancer patients to assess tumor burden, track therapy response, or detect early relapse. Common Cytokeratin MarkersAE1 / AE3: A cocktail of antibodies acting as a broad-spectrum screener for almost all carcinomas. CK5 / CK5/6: Key indicators for squamous cell carcinomas, mesotheliomas, and basal cells of the prostate or breast. CK7: Used to distinguish lung, breast, and ovarian cancers from gastrointestinal carcinomas. CK8 / CK18: Typically found in glandular and simple epithelia. Reduced expression often correlates with tumor progression in breast and colorectal adenocarcinomas. CAM 5.2: A low-molecular-weight cytokeratin marker frequently utilized to stain neuroendocrine tumors and certain adenocarcinomas.
B73: Cytokeratin-18 M30 fragment | C73: =VLOOKUP(B73,Class!B:B,2,FALSE) -> #N/A
B74: Cytokeratin-18 M65 fragment | C74: =VLOOKUP(B74,Class!B:B,2,FALSE) -> #N/A
B75: Total CK-18 | C75: =VLOOKUP(B75,Class!B:B,2,FALSE) -> #N/A
B76: Cell Death Markers | C76: =VLOOKUP(B76,Class!B:B,2,FALSE) -> #N/A | F76: Cell death markers are biological molecules used to detect and measure specific cell death pathways, such as apoptosis or necrosis. They enable researchers and clinicians to visualize cell damage, determine the mechanism of cell death, and track disease progression in samples like tissue slides or blood. The main types of cell death markers include: Apoptosis Markers: These detect programmed cell death. Common examples include Active Caspase-3 (an executioner enzyme that dismantles the cell), Cytochrome c (released from mitochondria to activate caspases), and Annexin V (which binds to phosphatidylserine flipped to the outer cell membrane in early apoptosis). Necrosis Markers: These identify unregulated, inflammatory cell death caused by trauma or toxicity. Common markers include HMGB1 (a nuclear protein released extracellularly) and cytosolic enzymes like LDHA (Lactate dehydrogenase A). Dye Exclusion Markers: Impermeable dyes like Propidium Iodide (PI) or DAPI are used to identify cells with compromised membranes (typical of necrosis or late apoptosis) while sparing viable cells
B77: Caspase-cleaved CK-18 | C77: =VLOOKUP(B77,Class!B:B,2,FALSE) -> #N/A
B78: Soluble Fas | C78: =VLOOKUP(B78,Class!B:B,2,FALSE) -> #N/A
B79: Fas ligand | C79: =VLOOKUP(B79,Class!B:B,2,FALSE) -> #N/A
B80: 6. Oxidative Stress Biomarkers | C80: =VLOOKUP(B80,Class!B:B,2,FALSE) -> #N/A | F80: Oxidative stress biomarkers are measurable molecular indicators that evaluate the imbalance between the production of reactive oxygen species (ROS) and the body's antioxidant defenses. They represent the resulting damage to lipids, proteins, and DNA, helping researchers and clinicians assess disease progression, cellular aging, and metabolic health. The primary categories of these biomarkers, alongside key clinical examples, include: Lipid Peroxidation Products: Indicate damage to cell membranes. Common markers include Malondialdehyde (MDA), 4-hydroxynonenal (4-HNE), and Isoprostanes. Assays like the TBARS test are frequently utilized to quantify these. Protein Oxidation Markers: Reflect structural damage and enzyme inactivation. The most established markers are Protein Carbonyls and Advanced Oxidation Protein Products (AOPP). Nucleic Acid Damage: Highlight oxidative lesions to DNA and RNA, which can lead to genomic instability. The most common marker is 8-hydroxydeoxyguanosine (8-OHdG). Antioxidant Capacity: Measure the body's protective resources, rather than damage. This includes tracking enzymes like Superoxide Dismutase (SOD), Catalase, and Glutathione (GSH). Exploring these markers is crucial for understanding systemic inflammation and managing conditions like diabetes, cardiovascular diseases, and neurodegenerative disorders.
B81: Lipid Peroxidation | C81: =VLOOKUP(B81,Class!B:B,2,FALSE) -> #N/A | F81: Lipid peroxidation is the oxidative degradation of lipids in cell membranes, primarily affecting polyunsaturated fatty acids (PUFAs). Initiated by free radicals or reactive oxygen species (ROS), it triggers a destructive chain reaction that compromises membrane integrity and produces toxic byproducts, contributing to various diseases and cell aging. The process unfolds in three primary stages:Initiation: A free radical (like a hydroxyl radical) steals a hydrogen atom from a lipid molecule, converting the lipid into a reactive free radical. Propagation: The unstable lipid radical reacts with molecular oxygen, forming a peroxyl radical. This radical then abstracts a hydrogen atom from an adjacent lipid, propagating the cycle and creating lipid hydroperoxides. Termination: Two free radicals combine with each other to form a stable, non-radical product, halting the chain reaction. This can also be achieved when antioxidants donate electrons to stabilize the radicals. Common Outcomes: As lipid hydroperoxides break down, they yield highly reactive aldehydes, such as malondialdehyde (MDA) and 4-hydroxynonenal (4-HNE). These compounds can further damage proteins and DNA. In physiological contexts, unchecked peroxidation is linked to conditions like atherosclerosis, neurodegenerative diseases, and ferroptosis.
B82: Malondialdehyde (MDA) | C82: =VLOOKUP(B82,Class!B:B,2,FALSE) -> #REF!
B83: 4-Hydroxynonenal (4-HNE) | C83: =VLOOKUP(B83,Class!B:B,2,FALSE) -> #N/A
B84: F2-Isoprostanes | C84: =VLOOKUP(B84,Class!B:B,2,FALSE) -> #N/A
B85: Antioxidant Defense | C85: =VLOOKUP(B85,Class!B:B,2,FALSE) -> #N/A | F85: The antioxidant defense system is a sophisticated multi-layered biological network of enzymes and small molecules that neutralizes reactive oxygen species (ROS). By converting dangerous free radicals into harmless byproducts, it protects vital cellular components like lipids, proteins, and DNA from the irreversible damage known as oxidative stress. To ensure thorough protection, this mechanism operates in distinct, overlapping stages: Primary Defense (Enzymatic Scavengers): The body's first responders are specialized proteins that intercept free radicals right at the source. Key enzymes include: Superoxide Dismutase (SOD): Catalyzes the conversion of highly reactive superoxide radicals into the less harmful hydrogen peroxide. Catalase (CAT): Immediately breaks down hydrogen peroxide into harmless water and oxygen. Glutathione Peroxidase (GPx): A selenium-dependent enzyme that reduces hydrogen peroxide and lipid peroxides. Secondary Defense (Non-Enzymatic Antioxidants): When initial enzymes are overwhelmed, these molecules sweep through cells to neutralize remaining radicals and stop chain reactions. This includes exogenous, diet-derived compounds like Vitamin C, Vitamin E, carotenoids, and the tripeptide glutathione
B86: Superoxide dismutase (SOD) | C86: =VLOOKUP(B86,Class!B:B,2,FALSE) -> #REF!
B87: Catalase (CAT) | C87: =VLOOKUP(B87,Class!B:B,2,FALSE) -> #N/A
B88: Glutathione (GSH) | C88: =VLOOKUP(B88,Class!B:B,2,FALSE) -> #REF!
B89: Glutathione peroxidase (GPx) | C89: =VLOOKUP(B89,Class!B:B,2,FALSE) -> #N/A
B90: Reactive Species Markers | C90: =VLOOKUP(B90,Class!B:B,2,FALSE) -> #N/A | F90: Reactive species markers are molecules, enzymes, or cellular changes used to measure oxidative stress the harmful state where the production of unstable, oxygen- or nitrogen-containing molecules outpaces the body's antioxidant defenses. These markers help scientists and doctors evaluate cellular damage linked to diseases like cancer and heart disease. Because free radicals are highly unstable and difficult to measure directly, researchers track the "scars" or damage they leave behind on biological molecules. The most common markers include: DNA and RNA Damage: 8-OHdG (8-hydroxydeoxyguanosine) is the most widely used marker for oxidative DNA damage. High levels indicate genomic instability, which is often tied to cancer and aging. Lipid Peroxidation: MDA (malondialdehyde) and 4-HNE are markers that measure the destruction of cell membranes by free radicals. Protein Oxidation: 3-Nitrotyrosine (3-NT) is a biomarker used to detect damage to proteins caused by reactive nitrogen species (RNS). Antioxidant Capacity: Assays like ORAC (Oxygen Radical Absorbance Capacity) measure the total capability of blood or tissue to neutralize these reactive species
B91: Nitric oxide (NO) | C91: =VLOOKUP(B91,Class!B:B,2,FALSE) -> #N/A
B92: Total antioxidant capacity (TAC) | C92: =VLOOKUP(B92,Class!B:B,2,FALSE) -> #N/A
B93: 7. Adipokines | C93: =VLOOKUP(B93,Class!B:B,2,FALSE) -> #N/A | F93: Adipokines are a large group of signaling proteins and hormones secreted by adipose (fat) tissue. They act as the body's messengers, regulating crucial functions such as appetite, energy balance, glucose metabolism, and inflammation.Adipose tissue is not just an energy storage depot; it is an active endocrine organ that produces hundreds of different adipokines. They are broadly categorized into two types: 1. Anti-inflammatory AdipokinesThese molecules are cardioprotective, improve insulin sensitivity, and help prevent blood vessel disease (atherosclerosis). Adiponectin: Enhances the body's ability to break down fat and use insulin. High levels are generally healthy, though levels often decrease as fat mass increases. Omentin and CTRPs: These help reduce systemic inflammation and support normal glucose metabolism. 2. Pro-inflammatory AdipokinesThese molecules are linked to systemic inflammation and conditions like insulin resistance, metabolic syndrome, and cardiovascular disease. Leptin: Often called the "satiety hormone," it communicates with the brain to regulate hunger and energy expenditure. In obesity, individuals often develop "leptin resistance," where the brain stops responding to its signals. Resistin: This adipokine is associated with the development of insulin resistance and type 2 diabetes. Chemerin and Visfatin: These contribute to inflammation and can negatively impact metabolic and cardiovascular health. The Role in Health and DiseaseIn a healthy state, pro- and anti-inflammatory adipokines remain in balance. However, when visceral fat deposits expand and adipocytes (fat cells) become dysfunctional, this equilibrium is disrupted. The overproduction of pro-inflammatory adipokines leads to "metabolic inflammation," contributing to chronic conditions like diabetes, obesity, and heart disease.
B94: Protective Adipokines | C94: =VLOOKUP(B94,Class!B:B,2,FALSE) -> #N/A | F94: Protective adipokines are beneficial, anti-inflammatory hormone proteins secreted by adipose (fat) tissue. They regulate whole-body metabolism, increase insulin sensitivity, and protect the cardiovascular system. During obesity, the production of these protective molecules often drops, accelerating metabolic and cardiovascular diseases. Key Protective AdipokinesAdiponectin: The most abundant protective adipokine. It enhances insulin sensitivity (preventing Type 2 diabetes), burns fat, and lowers vascular inflammation to protect against atherosclerosis. Omentin: Primarily secreted by visceral fat. It promotes insulin-mediated glucose uptake and exhibits strong anti-inflammatory and anti-atherosclerotic properties. FGF21 (Fibroblast Growth Factor 21): A crucial metabolic regulator that improves energy expenditure, lipid profiles, and prevents metabolic dysfunction. CTRP9 (C1q/TNF-Related Protein 9): Shares receptors with adiponectin and works alongside it to relax blood vessels, inhibit vascular disease, and improve glucose tolerance. Neuregulin 4 (NRG4): Secreted largely by brown adipose tissue. It helps prevent obesity-associated metabolic disorders and promotes healthy energy expenditure. Vaspin: Acts to improve insulin sensitivity and exerts protective, anti-inflammatory effects on vascular endothelial cells. Biological Roles & Mechanisms Anti-Inflammatory: They actively suppress destructive, pro-inflammatory cytokines (such as TNF-α and IL-6) to stop systemic inflammation. Metabolic Regulation: They stimulate glucose uptake in muscles and suppress excessive glucose production in the liver. Cardioprotection: They prevent the formation of "foam cells" in blood vessels and promote vasodilation (widening of blood vessels), lowering the risk of heart attacks and strokes.
B95: Adiponectin | C95: =VLOOKUP(B95,Class!B:B,2,FALSE) -> #REF!
B96: Omentin-1 | C96: =VLOOKUP(B96,Class!B:B,2,FALSE) -> #N/A
B97: Pro-inflammatory Adipokines | C97: =VLOOKUP(B97,Class!B:B,2,FALSE) -> #N/A | F97: Pro-inflammatory adipokines are signaling proteins and hormones secreted by adipose (fat) tissue that promote immune cell recruitment and chronic low-grade inflammation. Often elevated in obesity, they trigger systemic metabolic dysfunction, notably insulin resistance, by disrupting normal cellular signaling pathways. Adipose tissue is not just an energy storage depot; it acts as a major endocrine organ that secretes hundreds of different molecules, including both pro- and anti-inflammatory factors. Under healthy, lean conditions, the body maintains a delicate balance, but excess fat accumulation creates hypertrophic (enlarged) adipocytes that become oxygen-starved. This cellular stress recruits immune cells (like macrophages) into the fat tissue, fundamentally shifting the balance to favor pro-inflammatory adipokines. Key pro-inflammatory adipokines include: Leptin: Best known for regulating appetite and energy expenditure, it increases in direct proportion to body fat mass and acts as a potent immune-system stimulator. Tumor Necrosis Factor-alpha (TNF-α): A major cytokine that inhibits insulin-induced glucose uptake and directly triggers insulin resistance. Interleukin-6 (IL-6): Secreted heavily by enlarged adipocytes and infiltrating macrophages, it serves as a primary driver of systemic inflammation and is strongly linked to type 2 diabetes. Resistin: A polypeptide known to block insulin's actions and promote vascular/thrombosis-related issues. Other Markers: Include factors like Monocyte Chemoattractant Protein-1 (MCP-1) and Retinol Binding Protein 4 (RBP-4), which further exacerbate inflammation
B98: Leptin | C98: =VLOOKUP(B98,Class!B:B,2,FALSE) -> #REF!
B99: Resistin | C99: =VLOOKUP(B99,Class!B:B,2,FALSE) -> #REF!
B100: Visfatin | C100: =VLOOKUP(B100,Class!B:B,2,FALSE) -> #N/A
...

Sheet Blood and Serum
A1: Type | B1: Biomarker_ID | C1: Description
A2: Blood & Serum Biomarkers | B2: 1. Liver Injury Biomarkers | C2: Liver injury biomarkers are blood tests measuring enzymes and proteins that leak into the bloodstream when liver cells are damaged or when the liver's function is impaired. They are essential for diagnosing, localizing, and monitoring conditions such as hepatitis, cirrhosis, and drug-induced liver injury (DILI).
B3: Routine Liver Function Tests | C3: Routine Liver Function Tests (LFTs) are a group of blood tests used to measure specific enzymes, proteins, and substances to assess overall liver health, screen for infections like hepatitis, monitor medication side effects, and diagnose or monitor liver diseases. The primary components typically measured in a standard LFT profile include: Alanine Aminotransferase (ALT) and Aspartate Aminotransferase (AST): Enzymes concentrated in liver cells. Elevated levels in the bloodstream indicate liver cell injury or inflammation. Alkaline Phosphatase (ALP): An enzyme found in the liver and bones. High levels can suggest issues with the bile ducts or liver damage. Bilirubin: A waste product produced when red blood cells break down, which the liver is responsible for clearing. Elevated levels can cause jaundice and indicate liver disease or blocked bile ducts. Albumin and Total Protein: Albumin is a vital protein created exclusively by the liver, and total protein measures all the proteins in the blood. Low levels can indicate that the liver is not producing proteins properly or may point to chronic kidney/liver conditions. Gamma-glutamyl Transferase (GGT): An enzyme often added to screen for liver and bile duct stress or damage, particularly from alcohol use. Prothrombin Time (PT): Measures how long your blood takes to clot. Because the liver produces clotting factors, an abnormal PT time can indicate impaired liver function.
B4: Alanine aminotransferase (ALT)
B5: Aspartate aminotransferase (AST)
B6: Gamma-glutamyl transferase (GGT)
B7: Alkaline phosphatase (ALP)
B8: Lactate dehydrogenase (LDH)
B9: Total bilirubin
B10: Direct bilirubin
B11: Indirect bilirubin
B12: Liver Synthetic Function | C12: Liver synthetic function is the organ's ability to produce essential blood proteins, coagulation factors, and biochemical molecules. It is clinically assessed by measuring serum albumin (for chronic capacity) and prothrombin time/INR (for acute capacity). Core Synthetic ProcessesProtein Synthesis: The liver produces roughly 90% of circulating blood proteins, most notably albumin. Albumin maintains intravascular oncotic pressure and transports hormones, fatty acids, and drugs. It also synthesizes carrier proteins like transferrin (for iron transport). Coagulation Factors: The liver is the primary site of synthesis for nearly all clotting factors (e.g., fibrinogen, prothrombin, factors V, VII, IX, and X). It also synthesizes natural anticoagulants like protein C and protein S. Metabolite and Energy Production: The liver continuously synthesizes lipids, cholesterol (to build cell membranes and bile acids), and lipoproteins. During fasting, it synthesizes glucose (gluconeogenesis) and produces ketone bodies as alternative brain fuel. Regulatory Molecules: It creates key hormones and regulatory proteins, such as thrombopoietin (which stimulates platelet production) and angiotensinogen (which regulates blood pressure). Clinical Significance & Testing Because the liver has a large functional reserve, synthetic function typically remains well-preserved until liver disease becomes advanced or chronic (e.g., cirrhosis). Albumin Testing: Albumin has a long circulatory half-life (about 21 days). A low serum level (hypoalbuminemia) indicates long-term, chronic liver impairment or severe malnutrition. PT/INR Testing: The liver's coagulation factors have much shorter half-lives. Prolonged prothrombin time (PT) or an elevated international normalized ratio (INR) serves as a highly sensitive, acute indicator of failing synthetic capacity and elevated bleeding risk.
B13: Albumin
B14: Total protein
B15: Globulin
B16: Albumin/Globulin ratio
B17: Prothrombin time (PT)
B18: International Normalized Ratio (INR)
B19: 2. Metabolic Biomarkers | C19: Metabolic biomarkers are measurable biological indicators such as specific molecules or hormones in blood or urine that reflect how your body processes and utilizes energy. They are crucial for diagnosing metabolic conditions (like diabetes and cardiovascular disease), tracking organ function, and evaluating your overall physiological health. The most critical metabolic biomarkers are often grouped into a standard metabolic panel: Blood Glucose & Insulin: Measures your body's ability to process sugars. Indicators like fasting glucose and HbA1c (average blood sugar over 3 months) identify risks for insulin resistance and type 2 diabetes. Lipid Profile: Tracks fat-based particles in your blood. Key markers include triglycerides, HDL (high-density lipoprotein/"good" cholesterol), and LDL (low-density lipoprotein/"bad" cholesterol) to assess cardiovascular risk. Liver & Kidney Markers: Biomarkers like ALT (alanine aminotransferase) for liver health and BUN/Creatinine for kidney function help catch organ stress or damage early. Inflammatory Markers: Proteins like hs-CRP (high-sensitivity C-reactive protein) indicate chronic, low-grade inflammation, which is often tied to metabolic syndrome
B20: Glucose Metabolism | C20: Glucose metabolism refers to the bodily processes that break down, utilize, and store glucose (sugar) from food. It is the primary way your cells generate energy to keep your body functioning. How the Process Works? Glucose metabolism encompasses a few key, continuous processes to manage energy:Glycolysis: The breakdown of glucose in cells to produce immediate energy in the form of ATP (Adenosine Triphosphate).Glycogenesis: The synthesis and storage of excess glucose as glycogen (primarily in the liver and muscles) for later use.Glycogenolysis: The breakdown of stored glycogen back into glucose when blood sugar is low (like during sleep or fasting).Gluconeogenesis: The synthesis of new glucose from non-carbohydrate sources, such as amino acids, when energy reserves are depleted. The Role of Hormones This intricate process is heavily regulated by hormones released by the pancreas:Insulin: Secreted after a meal to lower blood sugar. It acts as a key, unlocking cell membranes so glucose can enter tissue cells for energy or storage.Glucagon: Secreted during fasting to raise blood sugar. It signals the liver to convert stored glycogen back into glucose. Why It Matters? Glucose is the essential fuel source for nearly all cells, especially the brain and nervous system. When glucose metabolism functions normally, your body maintains a healthy, balanced blood sugar level.Impairments or breakdowns in this system such as insulin resistance, where cells fail to respond effectively to insulin often lead to conditions like prediabetes or type 2 diabetes.
B21: Fasting blood glucose (FBG)
B22: Random blood glucose
B23: Hemoglobin A1c (HbA1c)
B24: Fasting insulin
B25: C-peptide
B26: HOMA-IR
B27: HOMA-β
B28: Lipid Profile | C28: A lipid profile (or lipid panel) is a blood test that measures the amount of cholesterol and other fats in your blood. It is a crucial screening tool used by doctors to assess your cardiovascular health and determine your risk for developing heart disease, blockages in your arteries, or having a stroke. A standard lipid profile typically measures the following specific components: Total Cholesterol: The overall amount of cholesterol circulating in your bloodstream (including both "good" and "bad" types). Optimal Level: Below 200 mg/dL.Low-Density Lipoprotein (LDL) Cholesterol: Often referred to as "bad cholesterol". High levels can build up in the walls of your blood vessels, forming plaque that restricts blood flow and increases the risk of heart attacks. Optimal Level: Below 100 mg/dL. High-Density Lipoprotein (HDL) Cholesterol: Known as "good cholesterol". It actively sweeps excess cholesterol out of your bloodstream and transports it back to the liver to be broken down, offering protection against heart disease. Optimal Level: 60 mg/dL or higher. Triglycerides: A type of fat (lipid) that your body makes from excess calories and the food you eat. They are stored in your fat cells for energy, but high levels are linked to a higher risk of heart disease and insulin resistance. Optimal Level: Below 150 mg/dL. Very Low-Density Lipoprotein (VLDL) Cholesterol: Often calculated based on your triglyceride level. VLDL mainly carries triglycerides in the blood and high levels can also indicate a risk of artery blockages. Optimal Level: Below 30 mg/dL
B29: Total cholesterol
B30: Triglycerides
B31: HDL cholesterol
B32: LDL cholesterol
B33: VLDL cholesterol
B34: Non-HDL cholesterol
B35: Free fatty acids (FFA)
B36: Apolipoprotein A1
B37: Apolipoprotein B
B38: Lipoprotein(a)
B39: 3. Inflammatory Biomarkers | C39: Inflammatory biomarkers are measurable substances in the body such as proteins, enzymes, and cells that indicate the presence and severity of inflammation. Doctors use blood or stool tests to detect these markers, which helps diagnose infections, autoimmune diseases, and chronic conditions like heart disease or inflammatory bowel disease. Because inflammatory biomarkers are typically non-specific meaning an elevated level signals inflammation but rarely points to a single, exact cause they are usually ordered alongside a thorough physical exam and clinical history. The most common inflammatory biomarkers include: C-Reactive Protein (CRP): Produced by the liver, CRP is the most widely used marker to detect acute inflammation caused by severe infections, tissue damage, or autoimmune flare-ups. A specialized version, hs-CRP (High-Sensitivity CRP), is used to measure low-grade chronic inflammation and assess cardiovascular risk. Erythrocyte Sedimentation Rate (ESR): This test measures how quickly red blood cells settle in a test tube. Inflammatory proteins cause red blood cells to clump and settle faster, signaling ongoing inflammation. Cytokines: These are small signaling proteins (such as Interleukin-6 and TNF-alpha) that regulate immune responses. They are often elevated in severe inflammatory conditions and cancers. Procalcitonin (PCT): This marker is particularly useful for detecting severe bacterial infections and guiding antibiotic therapy, especially in cases of sepsis. Plasma Viscosity (PV): Similar to ESR, this measures the thickness of blood plasma. It is sometimes preferred over ESR because it is not affected by a patient's age or sex. Calprotectin: Frequently measured in stool samples, this protein is a highly reliable biomarker for intestinal inflammation, aiding in the diagnosis and monitoring of Inflammatory Bowel Disease (IBD)
B40: Cytokines | C40: Cytokines are small proteins secreted by cells that act as chemical messengers. They are essential for regulating the immune system, controlling inflammation, and dictating how cells grow and divide. When the body faces an infection or injury, immune and non-immune cells release cytokines to coordinate a targeted defense. Key Types of Cytokines Cytokines are categorized into several major groups based on their structure and function: Interleukins (ILs): Regulate immune and inflammatory responses, often acting as messengers between different white blood cells. Chemokines: Direct immune cells to the specific site of an infection or tissue damage through a process called chemotaxis. Interferons (IFNs): Help defend against viruses by preventing them from multiplying and stimulating other immune cells to fight the infection. Tumor Necrosis Factors (TNFs): Help trigger inflammation and can directly destroy certain types of cells, including cancer cells. Colony-Stimulating Factors (CSFs): Stimulate the bone marrow to produce and differentiate new blood and immune cells. How They Work? Cytokines operate by binding to specific receptors on the surface of target cells. This binding triggers a chain reaction inside the cell that tells it to grow, die, or move. They act in three primary ways: Autocrine: A cell secretes cytokines to signal itself. Paracrine: A cell secretes cytokines to signal nearby, neighboring cells. Endocrine: Cytokines enter the bloodstream to signal distant cells or organs (e.g., triggering a fever in the brain). Medical Relevance! Because they dictate how the body responds to illness, cytokines are heavily studied in medicine. An overreaction of the immune system can cause a dangerous flood of cytokines, known as a cytokine storm, which can damage healthy tissues. Conversely, lab-made versions of cytokines (like Interleukin-2) are used as immunotherapies to treat certain conditions, such as advanced kidney cancer and metastatic melanoma.
B41: Tumor necrosis factor-alpha (TNF-α)
B42: Interleukin-1β (IL-1β)
B43: Interleukin-6 (IL-6)
B44: Interleukin-8 (IL-8)
B45: Interleukin-18 (IL-18)
B46: Interleukin-17 (IL-17)
B47: Chemokines | C47: Chemokines are a family of small, secreted signaling proteins that act as chemoattractants. They direct the movement of white blood cells and other cells through the body by inducing directional migration (chemotaxis) along a chemical gradient.They play crucial roles in maintaining the immune system, mounting inflammatory responses to fight infections, and managing normal tissue growth. Key Characteristics Size & Structure: They are small proteins, roughly 8–10 kilodaltons, defined by specific, conserved cysteine residues. Classification: They are grouped into four main sub-families based on the arrangement of their initial cysteine amino acids: CC, CXC, C, and CX3C. Receptors: Chemokines exert their effects by binding to specific G protein-coupled receptors (GPCRs) on the surface of target cells. Primary Functions Inflammation: They act as alarm signals. When a tissue is injured or infected, cells secrete chemokines to attract immune cells like neutrophils and macrophages to the affected area to fight the pathogen and heal the wound. Homeostasis: Some chemokines are continuously active, managing the regular movement and development of immune cells throughout healthy tissues and organs. Cell Signaling: By binding to their receptors, chemokines trigger intracellular signaling cascades that not only direct cell movement but also promote cell survival and growth. Because of their critical role in cell trafficking, chemokines are also heavily involved in various disease processes, including autoimmune disorders, tumor growth, and viral infections
B48: Monocyte chemoattractant protein-1 (MCP-1/CCL2)
B49: CCL5 (RANTES)
B50: CXCL10
B51: Acute Phase Proteins | C51: Acute Phase Proteins are blood proteins synthesized by the liver that change in concentration by at least 25% in response to inflammation, infection, or tissue injury. They form a core part of the innate immune response, helping to clear pathogens, neutralize harmful enzymes, and restore bodily homeostasis. These proteins are broadly classified into two main categories: Positive Acute Phase Proteins: Their levels increase in the blood. They actively aid in fighting infection and inflammation. Common examples include: C-Reactive Protein (CRP): Promotes phagocytosis (engulfing of pathogens) and activates the complement system. Fibrinogen: Aids in blood clot formation to limit the spread of infections. Ferritin: Binds and sequesters iron, which deprives invading bacteria of a vital nutrient. Serum Amyloid A (SAA): Helps recruit inflammatory cells to the site of injury or infection. Negative Acute Phase Proteins: Their levels decrease in the blood. The liver reduces the synthesis of these proteins to conserve amino acids and energy, prioritizing the production of positive acute phase proteins. Common examples include albumin and transferrin. The production of these proteins is triggered by immune signaling molecules, primarily cytokines like IL-6, IL-1, and TNF-α. Because their levels shift rapidly, acute phase proteins (especially CRP) are frequently used as clinical biomarkers to detect, diagnose, and monitor the severity of inflammatory diseases and infections
B52: High-sensitivity C-reactive protein (hs-CRP)
B53: Serum amyloid A (SAA)
B54: Ferritin
B55: 4. Fibrosis Biomarkers | C55: Fibrosis biomarkers are measurable biological molecules in blood, tissue, or bodily fluids that indicate the presence and severity of scar tissue (fibrosis) in organs like the liver, lungs, or kidneys. They provide vital, non-invasive alternatives to biopsies for diagnosing and monitoring disease progression. These diagnostic tools are typically categorized into two main types: Direct Biomarkers: These measure the actual turnover of extracellular matrix (ECM) proteins, such as collagens, which are deposited during scarring. Examples include Hyaluronic Acid (HA), Procollagen III Amino-Terminal Peptide (PIIINP), and Tissue Inhibitors of Metalloproteinase-1 (TIMP-1). Tests like the Enhanced Liver Fibrosis (ELF) test combine these direct markers to gauge advanced disease. Indirect Biomarkers: These are calculated scores derived from routine lab tests that reflect organ dysfunction caused by fibrosis. Common examples include the FIB-4 Index (based on age, AST, ALT, and platelets) and the APRI score (based on AST and platelet counts). In addition to liver disease, biomarkers play a crucial role in conditions like Idiopathic Pulmonary Fibrosis (IPF) in the lungs, where proteins such as Periostin and Galectin-3 are used to predict lung function decline
B56: Extracellular Matrix Components | C56: The Extracellular Matrix (ECM) is a dynamic, 3D network of macromolecules (like proteins and polysaccharides) that fills the spaces between cells. It provides crucial structural scaffolding, mechanical support, and biochemical signaling to guide cell growth, migration, and tissue organization.The ECM's primary functional components include: Collagen: The most abundant protein in the ECM. It forms triple-helix fibrils that provide vital tensile strength and structural integrity to tissues like skin, tendons, and bones. Elastin: A highly elastic, cross-linked fibrous protein that allows tissues (such as the lungs and blood vessels) to stretch and recoil back to their original shape. Proteoglycans: Heavily glycosylated proteins that trap water to form a hydrated, gel-like "ground substance". They act as a compression buffer and a reservoir for growth factors. Glycosaminoglycans (GAGs): Long, unbranched chains of polysaccharides (e.g., hyaluronan) that attach to proteoglycans to absorb immense compression forces. Fibronectin & Laminin: Multi-adhesive glycoproteins that physically link the ECM to the cell membrane (via integrins), allowing for vital cell-to-cell communication and migration
B57: Hyaluronic acid (HA)
B58: Type IV collagen
B59: Type III collagen
B60: Laminin
B61: Fibrogenesis Markers | C61: Fibrogenesis markers are clinical indicators that measure the body's active process of laying down fibrous, scar-forming connective tissue (extracellular matrix) in organs, most commonly the liver. They are primarily categorized into Direct (Class I) and Indirect (Class II) markers to assess disease activity and progression. Direct (Class I) Markers: These specifically measure the molecules involved in extracellular matrix (ECM) turnover, such as the synthesis or degradation of collagen. They indicate "what is going on" with the actual fibrogenic process. Common examples include Hyaluronic acid (HA), Procollagen type III N-terminal peptide (PIIINP), and Laminin. Indirect (Class II) Markers: These are routine, empiric laboratory tests that reflect overall organ dysfunction caused by scarring (e.g., liver function) rather than ECM production itself. They help establish the "stage" of fibrosis. Examples include AST/ALT ratios, Platelet counts, Bilirubin, and algorithms like the FIB-4 score and APRI
B62: Procollagen III N-terminal peptide (PIIINP)
B63: Tissue inhibitor of metalloproteinase-1 (TIMP-1)
B64: Matrix metalloproteinase-2 (MMP-2)
B65: Matrix metalloproteinase-9 (MMP-9)
B66: Advanced Fibrosis Markers | C66: Advanced fibrosis markers are non-invasive blood tests and imaging tools used to assess the severity of liver scarring (fibrosis). They eliminate the need for painful liver biopsies by categorizing scarring into stages (usually F0-F4), with stages F3-F4 representing "advanced" fibrosis or cirrhosis. These assessments are broken down into two main categories: 1. Simple Blood Tests (Indirect Markers): These use standard, inexpensive, and widely available lab work to calculate a score based on liver function and systemic changes. FIB-4 Index: Calculates fibrosis risk based on a patient's age, platelet count, AST, and ALT levels. It is highly recommended by medical guidelines to rule out advanced fibrosis. NAFLD Fibrosis Score (NFS): Evaluates six factors: age, body mass index (BMI), platelet count, albumin, AST/ALT ratio, and presence of diabetes/hyperglycemia. APRI (AST to Platelet Ratio Index): Uses AST levels and platelet counts to quickly predict significant fibrosis. 2. Specialized Blood Tests (Direct Markers): These complex panels measure molecules actively involved in the creation or breakdown of scar tissue (fibrogenesis). ELF (Enhanced Liver Fibrosis) Test: Combines measurements of hyaluronic acid (HA), amino-terminal propeptide of type III procollagen (PIIINP), and tissue inhibitor of metalloproteinase 1 (TIMP-1). It is highly accurate in assessing advanced fibrosis across various chronic liver diseases. FibroTest / FibroSure: Measures components like alpha-2-macroglobulin, haptoglobin, total bilirubin, and GGT to gauge fibrosis levels. 3. Imaging Modalities (Elastography): Imaging tests measure the actual physical stiffness of the liver tissue a stiffer liver corresponds to a higher degree of fibrosis. FibroScan (VCTE): Uses specialized ultrasound waves to measure liver stiffness and estimate fat content (CAP scores). Magnetic Resonance Elastography (MRE): Considered the most accurate non-invasive imaging method for mapping fibrosis severity across the entire liver.
B67: YKL-40 (CHI3L1)
B68: Osteopontin (OPN)
B69: Connective tissue growth factor (CTGF)
B70: Transforming growth factor-beta (TGF-β1)
B71: 5. Hepatocyte Apoptosis Biomarkers | C71: Hepatocyte apoptosis biomarkers are indicators used to detect and quantify programmed liver cell death. They are primarily used in non-invasive blood tests to assess the severity of liver diseases such as NASH, viral hepatitis, and alcoholic liver disease without the need for a surgical liver biopsy. Core Biomarkers: Cytokeratin-18 (CK-18): The most widely used circulating biomarker for hepatocyte death. CK-18 is an abundant structural protein in liver cells. During apoptosis, it is cleaved by caspases. ccK18 (Caspase-cleaved CK-18 / M30 fragment): Specifically indicates apoptosis. Elevated levels are detected using the Peviva M30 Apoptosense Assay.Total CK18 / M65: Measures both apoptosis and necrosis (unregulated cell death). It is measured using the Peviva M65 ELISA. M30 : M65 Ratio: A metric used to determine whether the dominant form of cell death in the liver is apoptosis or necrosis.Underlying Pathways & Mechanisms These biomarkers reflect the two main pathways of apoptosis in hepatocytes: Extrinsic Pathway: Triggered when "death ligands" in the blood (such as FasL or TNF-α) bind to death receptors on the surface of the hepatocyte, initiating a chain of cell-death signals. Intrinsic Pathway: Triggered internally by cellular stressors like oxidative stress, endoplasmic reticulum (ER) stress, or mitochondrial dysfunction. This pathway involves the release of proteins like cytochrome c into the cell cytoplasm, activating executioner caspases (e.g., Caspase-3). Clinical SignificanceLiver Fibrosis and Disease Progression: High levels of apoptotic biomarkers correlate with disease severity, liver ballooning, and inflammation.Treatment Monitoring: These markers are highly valuable for tracking how well a patient is responding to therapies or lifestyle changes (e.g., exercise reducing apoptosis in NAFLD)
B72: Cytokeratin Markers | C72: Cytokeratins are structural proteins forming the internal framework (intermediate filaments) of epithelial cells. In diagnostic pathology, these markers are critical for identifying epithelial-derived cancers (carcinomas). Different combinations of cytokeratins (numbered 1-20) are highly specific to particular organs, allowing pathologists to pinpoint the exact origin of a tumor. Why Cytokeratin Markers Are Used? Epithelial Screening: Broad-spectrum markers like AE1/AE3 are used to confirm if a poorly differentiated tumor is a carcinoma rather than a lymphoma or sarcoma. Cancer Differentiation: Specific CKs map to specific tissues. For example, CK5/6 strongly points to squamous cell carcinoma or mesothelioma, while CK7 is useful for distinguishing between ovarian and gastrointestinal carcinomas. Blood-Based Tumor Monitoring: Soluble fragments of cytokeratins (such as CYFRA 21-1 and TPS) are measured in the blood of cancer patients to assess tumor burden, track therapy response, or detect early relapse. Common Cytokeratin MarkersAE1 / AE3: A cocktail of antibodies acting as a broad-spectrum screener for almost all carcinomas. CK5 / CK5/6: Key indicators for squamous cell carcinomas, mesotheliomas, and basal cells of the prostate or breast. CK7: Used to distinguish lung, breast, and ovarian cancers from gastrointestinal carcinomas. CK8 / CK18: Typically found in glandular and simple epithelia. Reduced expression often correlates with tumor progression in breast and colorectal adenocarcinomas. CAM 5.2: A low-molecular-weight cytokeratin marker frequently utilized to stain neuroendocrine tumors and certain adenocarcinomas.
B73: Cytokeratin-18 M30 fragment
B74: Cytokeratin-18 M65 fragment
B75: Total CK-18
B76: Cell Death Markers | C76: Cell death markers are biological molecules used to detect and measure specific cell death pathways, such as apoptosis or necrosis. They enable researchers and clinicians to visualize cell damage, determine the mechanism of cell death, and track disease progression in samples like tissue slides or blood. The main types of cell death markers include: Apoptosis Markers: These detect programmed cell death. Common examples include Active Caspase-3 (an executioner enzyme that dismantles the cell), Cytochrome c (released from mitochondria to activate caspases), and Annexin V (which binds to phosphatidylserine flipped to the outer cell membrane in early apoptosis). Necrosis Markers: These identify unregulated, inflammatory cell death caused by trauma or toxicity. Common markers include HMGB1 (a nuclear protein released extracellularly) and cytosolic enzymes like LDHA (Lactate dehydrogenase A). Dye Exclusion Markers: Impermeable dyes like Propidium Iodide (PI) or DAPI are used to identify cells with compromised membranes (typical of necrosis or late apoptosis) while sparing viable cells
B77: Caspase-cleaved CK-18
B78: Soluble Fas
B79: Fas ligand
B80: 6. Oxidative Stress Biomarkers | C80: Oxidative stress biomarkers are measurable molecular indicators that evaluate the imbalance between the production of reactive oxygen species (ROS) and the body's antioxidant defenses. They represent the resulting damage to lipids, proteins, and DNA, helping researchers and clinicians assess disease progression, cellular aging, and metabolic health. The primary categories of these biomarkers, alongside key clinical examples, include: Lipid Peroxidation Products: Indicate damage to cell membranes. Common markers include Malondialdehyde (MDA), 4-hydroxynonenal (4-HNE), and Isoprostanes. Assays like the TBARS test are frequently utilized to quantify these. Protein Oxidation Markers: Reflect structural damage and enzyme inactivation. The most established markers are Protein Carbonyls and Advanced Oxidation Protein Products (AOPP). Nucleic Acid Damage: Highlight oxidative lesions to DNA and RNA, which can lead to genomic instability. The most common marker is 8-hydroxydeoxyguanosine (8-OHdG). Antioxidant Capacity: Measure the body's protective resources, rather than damage. This includes tracking enzymes like Superoxide Dismutase (SOD), Catalase, and Glutathione (GSH). Exploring these markers is crucial for understanding systemic inflammation and managing conditions like diabetes, cardiovascular diseases, and neurodegenerative disorders.
B81: Lipid Peroxidation | C81: Lipid peroxidation is the oxidative degradation of lipids in cell membranes, primarily affecting polyunsaturated fatty acids (PUFAs). Initiated by free radicals or reactive oxygen species (ROS), it triggers a destructive chain reaction that compromises membrane integrity and produces toxic byproducts, contributing to various diseases and cell aging. The process unfolds in three primary stages:Initiation: A free radical (like a hydroxyl radical) steals a hydrogen atom from a lipid molecule, converting the lipid into a reactive free radical. Propagation: The unstable lipid radical reacts with molecular oxygen, forming a peroxyl radical. This radical then abstracts a hydrogen atom from an adjacent lipid, propagating the cycle and creating lipid hydroperoxides. Termination: Two free radicals combine with each other to form a stable, non-radical product, halting the chain reaction. This can also be achieved when antioxidants donate electrons to stabilize the radicals. Common Outcomes: As lipid hydroperoxides break down, they yield highly reactive aldehydes, such as malondialdehyde (MDA) and 4-hydroxynonenal (4-HNE). These compounds can further damage proteins and DNA. In physiological contexts, unchecked peroxidation is linked to conditions like atherosclerosis, neurodegenerative diseases, and ferroptosis.
B82: Malondialdehyde (MDA)
B83: 4-Hydroxynonenal (4-HNE)
B84: F2-Isoprostanes
B85: Antioxidant Defense | C85: The antioxidant defense system is a sophisticated multi-layered biological network of enzymes and small molecules that neutralizes reactive oxygen species (ROS). By converting dangerous free radicals into harmless byproducts, it protects vital cellular components like lipids, proteins, and DNA from the irreversible damage known as oxidative stress. To ensure thorough protection, this mechanism operates in distinct, overlapping stages: Primary Defense (Enzymatic Scavengers): The body's first responders are specialized proteins that intercept free radicals right at the source. Key enzymes include: Superoxide Dismutase (SOD): Catalyzes the conversion of highly reactive superoxide radicals into the less harmful hydrogen peroxide. Catalase (CAT): Immediately breaks down hydrogen peroxide into harmless water and oxygen. Glutathione Peroxidase (GPx): A selenium-dependent enzyme that reduces hydrogen peroxide and lipid peroxides. Secondary Defense (Non-Enzymatic Antioxidants): When initial enzymes are overwhelmed, these molecules sweep through cells to neutralize remaining radicals and stop chain reactions. This includes exogenous, diet-derived compounds like Vitamin C, Vitamin E, carotenoids, and the tripeptide glutathione
B86: Superoxide dismutase (SOD)
B87: Catalase (CAT)
B88: Glutathione (GSH)
B89: Glutathione peroxidase (GPx)
B90: Reactive Species Markers | C90: Reactive species markers are molecules, enzymes, or cellular changes used to measure oxidative stress the harmful state where the production of unstable, oxygen- or nitrogen-containing molecules outpaces the body's antioxidant defenses. These markers help scientists and doctors evaluate cellular damage linked to diseases like cancer and heart disease. Because free radicals are highly unstable and difficult to measure directly, researchers track the "scars" or damage they leave behind on biological molecules. The most common markers include: DNA and RNA Damage: 8-OHdG (8-hydroxydeoxyguanosine) is the most widely used marker for oxidative DNA damage. High levels indicate genomic instability, which is often tied to cancer and aging. Lipid Peroxidation: MDA (malondialdehyde) and 4-HNE are markers that measure the destruction of cell membranes by free radicals. Protein Oxidation: 3-Nitrotyrosine (3-NT) is a biomarker used to detect damage to proteins caused by reactive nitrogen species (RNS). Antioxidant Capacity: Assays like ORAC (Oxygen Radical Absorbance Capacity) measure the total capability of blood or tissue to neutralize these reactive species.
B91: Nitric oxide (NO)
B92: Total antioxidant capacity (TAC)
B93: 7. Adipokines | C93: Adipokines are a large group of signaling proteins and hormones secreted by adipose (fat) tissue. They act as the body's messengers, regulating crucial functions such as appetite, energy balance, glucose metabolism, and inflammation.Adipose tissue is not just an energy storage depot; it is an active endocrine organ that produces hundreds of different adipokines. They are broadly categorized into two types: 1. Anti-inflammatory AdipokinesThese molecules are cardioprotective, improve insulin sensitivity, and help prevent blood vessel disease (atherosclerosis). Adiponectin: Enhances the body's ability to break down fat and use insulin. High levels are generally healthy, though levels often decrease as fat mass increases. Omentin and CTRPs: These help reduce systemic inflammation and support normal glucose metabolism. 2. Pro-inflammatory AdipokinesThese molecules are linked to systemic inflammation and conditions like insulin resistance, metabolic syndrome, and cardiovascular disease. Leptin: Often called the "satiety hormone," it communicates with the brain to regulate hunger and energy expenditure. In obesity, individuals often develop "leptin resistance," where the brain stops responding to its signals. Resistin: This adipokine is associated with the development of insulin resistance and type 2 diabetes. Chemerin and Visfatin: These contribute to inflammation and can negatively impact metabolic and cardiovascular health. The Role in Health and DiseaseIn a healthy state, pro- and anti-inflammatory adipokines remain in balance. However, when visceral fat deposits expand and adipocytes (fat cells) become dysfunctional, this equilibrium is disrupted. The overproduction of pro-inflammatory adipokines leads to "metabolic inflammation," contributing to chronic conditions like diabetes, obesity, and heart disease.
B94: Protective Adipokines | C94: Protective adipokines are beneficial, anti-inflammatory hormone proteins secreted by adipose (fat) tissue. They regulate whole-body metabolism, increase insulin sensitivity, and protect the cardiovascular system. During obesity, the production of these protective molecules often drops, accelerating metabolic and cardiovascular diseases. Key Protective AdipokinesAdiponectin: The most abundant protective adipokine. It enhances insulin sensitivity (preventing Type 2 diabetes), burns fat, and lowers vascular inflammation to protect against atherosclerosis. Omentin: Primarily secreted by visceral fat. It promotes insulin-mediated glucose uptake and exhibits strong anti-inflammatory and anti-atherosclerotic properties. FGF21 (Fibroblast Growth Factor 21): A crucial metabolic regulator that improves energy expenditure, lipid profiles, and prevents metabolic dysfunction. CTRP9 (C1q/TNF-Related Protein 9): Shares receptors with adiponectin and works alongside it to relax blood vessels, inhibit vascular disease, and improve glucose tolerance. Neuregulin 4 (NRG4): Secreted largely by brown adipose tissue. It helps prevent obesity-associated metabolic disorders and promotes healthy energy expenditure. Vaspin: Acts to improve insulin sensitivity and exerts protective, anti-inflammatory effects on vascular endothelial cells. Biological Roles & Mechanisms Anti-Inflammatory: They actively suppress destructive, pro-inflammatory cytokines (such as TNF-α and IL-6) to stop systemic inflammation. Metabolic Regulation: They stimulate glucose uptake in muscles and suppress excessive glucose production in the liver. Cardioprotection: They prevent the formation of "foam cells" in blood vessels and promote vasodilation (widening of blood vessels), lowering the risk of heart attacks and strokes.
B95: Adiponectin
B96: Omentin-1
B97: Pro-inflammatory Adipokines | C97: Pro-inflammatory adipokines are signaling proteins and hormones secreted by adipose (fat) tissue that promote immune cell recruitment and chronic low-grade inflammation. Often elevated in obesity, they trigger systemic metabolic dysfunction, notably insulin resistance, by disrupting normal cellular signaling pathways. Adipose tissue is not just an energy storage depot; it acts as a major endocrine organ that secretes hundreds of different molecules, including both pro- and anti-inflammatory factors. Under healthy, lean conditions, the body maintains a delicate balance, but excess fat accumulation creates hypertrophic (enlarged) adipocytes that become oxygen-starved. This cellular stress recruits immune cells (like macrophages) into the fat tissue, fundamentally shifting the balance to favor pro-inflammatory adipokines. Key pro-inflammatory adipokines include: Leptin: Best known for regulating appetite and energy expenditure, it increases in direct proportion to body fat mass and acts as a potent immune-system stimulator. Tumor Necrosis Factor-alpha (TNF-α): A major cytokine that inhibits insulin-induced glucose uptake and directly triggers insulin resistance. Interleukin-6 (IL-6): Secreted heavily by enlarged adipocytes and infiltrating macrophages, it serves as a primary driver of systemic inflammation and is strongly linked to type 2 diabetes. Resistin: A polypeptide known to block insulin's actions and promote vascular/thrombosis-related issues. Other Markers: Include factors like Monocyte Chemoattractant Protein-1 (MCP-1) and Retinol Binding Protein 4 (RBP-4), which further exacerbate inflammation
B98: Leptin
B99: Resistin
B100: Visfatin
...

Sheet  Imaging-Based Biomarkers
A1: Type | B1: Biomarker_ID | C1: Description
A2: Imaging-Based Biomarkers | B2: 1. Ultrasound-Based Biomarkers | C2: Ultrasound-Based Biomarkers are quantitative imaging features (like tissue stiffness or microvascular flow) that provide objective, measurable indicators of normal biological processes, pathogenic processes, or responses to treatment. Instead of relying on visual assessment alone, these techniques extract actionable, mathematical data from ultrasound scans for early diagnosis and monitoring. The most common categories of ultrasound-based biomarkers include: Elastography (e.g., Shear Wave Elastography): Measures tissue stiffness. This is widely used in liver disease (to quantify fibrosis) and breast or thyroid imaging (to differentiate between benign and malignant lesions). Contrast-Enhanced Ultrasound (CEUS): Utilizes microbubble contrast agents to map blood flow and perfusion in real-time. This helps evaluate tumor vascularity and monitor how well a lesion responds to anti-cancer treatments. Quantitative Ultrasound (QUS) & Radiomics: Employs mathematical algorithms and computer models to analyze raw acoustic data (e.g., sound scattering and textural patterns). These biomarkers help predict molecular subtypes of cancer and evaluate tissue changes long before they become visible to the naked eye. Attitudinal & Dispersive Markers: Techniques like Attenuation Imaging (ATI) and Shear Wave Dispersion (SWD) are used to assess localized fat content (steatosis) and inflammation in conditions like non-alcoholic fatty liver disease (NAFLD). Sonobiopsy: An emerging, non-invasive focused ultrasound technique that gently opens the blood-brain barrier to release specific disease-related biomarkers directly into the bloodstream for analysis.
B3: Conventional Ultrasound | C3: A conventional ultrasound is a non-invasive medical imaging test that uses high-frequency sound waves to capture real-time images of the body’s internal organs, tissues, and structures. It works on the same principle as sonar, capturing returning echoes to map the size, shape, and consistency of targeted areas without using ionizing radiation. Here is a breakdown of how it works and what to expect: The Procedure: A trained technician (sonographer) applies a water-based gel to your skin and presses a handheld device called a transducer against the area being examined. The gel prevents air pockets from blocking the sound waves. The Physics: The transducer sends inaudible sound waves into your body. These waves bounce back as echoes whenever they hit a boundary between tissues (like between fluid and soft tissue, or soft tissue and bone). The transducer then converts these echoes into real-time digital images on a monitor. Common Applications: Because it involves no radiation, it is the primary method for monitoring fetal development during pregnancy. It is also widely used to examine abdominal organs (liver, kidneys, gallbladder), pelvic areas (uterus, ovaries), and soft tissue irregularities like cysts or tumors. Advantages: It is highly accessible, generally inexpensive compared to MRI or CT scans, captures movement in real-time, and has few (if any) contraindications
B4: Common first-line screening tool.
B5: Biomarkers
B6: Increased liver echogenicity ("bright liver")
B7: Hepatorenal contrast
B8: Vascular blurring
B9: Deep beam attenuation
B10: Liver-kidney echo ratio
B11: Quantitative Ultrasound Biomarkers | C11: Quantitative Ultrasound (QUS) Biomarkers are objective, system-independent measurements extracted from raw ultrasound radiofrequency (RF) data. Unlike conventional B-mode imaging, which is qualitative and heavily operator-dependent, QUS analyzes tissue microstructure to provide reproducible, numerical values for disease staging and treatment monitoring. Key QUS Parameters: The most widely used clinical QUS biomarkers include: Attenuation Coefficient: Measures the frequency-dependent loss of ultrasound energy as it travels through tissue. It is heavily utilized in hepatology to objectively grade liver fat content (steatosis). Backscatter Coefficient (BSC): Measures the intensity of ultrasound waves reflected by microscopic structures within the tissue. It is used to characterize tissue composition and detect changes related to diseases like fibrosis or tumors. Speed of Sound (SOS): Tracks the velocity at which ultrasound waves travel through tissue, which depends on tissue density and elasticity. This is crucial for evaluating both liver health and bone mineral density. Envelope Statistics: Analyzes the statistical distribution of backscattered echo amplitudes (e.g., Nakagami distribution) to capture microstructural variations that are invisible to the naked eye. Primary Clinical Applications Liver Disease: QUS provides a non-invasive, radiation-free method for diagnosing and grading Nonalcoholic Fatty Liver Disease (NAFLD) and liver fibrosis, serving as an alternative to painful biopsies. Oncology: Researchers utilize these biomarkers to evaluate tumor microenvironments, such as microvessel orientation, and to differentiate between benign and malignant masses in organs like the breast. Bone Health: Parameters like Broadband Ultrasound Attenuation (BUA) help quantify bone strength and trabecular microarchitecture without ionizing radiation.
B12: Attenuation coefficient (AC)
B13: Backscatter coefficient (BSC)
B14: Ultrasound-derived fat fraction (UDFF)
B15: Tissue scatter-distribution imaging
B16: 2. FibroScan-Based Biomarkers | C16: FibroScan-based biomarkers are composite diagnostic tools that combine a physical measurement of liver stiffness (via FibroScan / Vibration-Controlled Transient Elastography) with standard blood or clinical parameters. These algorithms provide highly accurate, non-invasive alternatives to traditional liver biopsies for staging liver scarring and fat content. These biomarkers integrate the two primary values measured by a FibroScan device: LSM (Liver Stiffness Measurement): Evaluates the degree of liver fibrosis or scarring (measured in kilopascals, kPa). CAP (Controlled Attenuation Parameter): Measures the amount of fat in the liver (steatosis, measured in decibels per meter, dB/m).By combining these physical metrics with patient data, doctors can accurately diagnose disease severity. The most widely used FibroScan-based biomarkers and indices include: 1. The FAST Score (FibroScan-AST) What it combines: Liver Stiffness (LSM), Controlled Attenuation Parameter (CAP), and AST (a liver enzyme from a blood test).Purpose: Primarily used to identify patients with active, progressive non-alcoholic steatohepatitis (NASH), now commonly referred to as MASH (Metabolic dysfunction-associated steatohepatitis). 2. The Agile 3+ and Agile 4 Scores What they combine: Liver Stiffness (LSM) along with clinical variables such as age, sex, AST, ALT, platelet count, and diabetes status. Purpose: These scoring algorithms are designed specifically for patients with fatty liver disease. Agile 3+ rules out or confirms advanced fibrosis, while Agile 4 is optimized to detect compensated cirrhosis. 3. MEFIB Index (Magnetic Resonance/FibroScan and FIB-4) What it combines: Liver stiffness parameters and the FIB-4 blood biomarker (which calculates age, AST, ALT, and platelet counts). Purpose: Helps clinicians reliably identify or exclude advanced fibrosis in patients with metabolic dysfunction-associated steatotic liver disease (MASLD). Advantages of Biomarker Combinations: Combining physical scans with blood tests overcomes the limitations of using either tool in isolation. For example, LSM values can be temporarily skewed by liver inflammation, but adding blood biomarkers into the algorithm corrects this. These tools are completely non-invasive, painless, and take only a few minutes to conduct.
B17: Controlled Attenuation Parameter (CAP) | C17: The Controlled Attenuation Parameter (CAP) is a non-invasive ultrasound technique used during a FibroScan to measure the amount of fat (hepatic steatosis) in the liver. It measures how ultrasound waves weaken as they pass through liver tissue and is expressed in decibels per meter (dB/m). CAP scores are reported on a scale from 100 to 400 dB/m. A score of less than 275 dB/m typically indicates little to no significant fatty liver. Scores above this threshold indicate significant hepatic steatosis, and the exact number helps clinicians grade the severity of the fat accumulation: Mild (S1): 238 to 259 dB/m Moderate (S2): 260 to 289 dB/m Severe (S3): ≥ 290 dB/m The primary advantage of CAP is that it evaluates fat non-invasively alongside liver stiffness (which checks for fibrosis/scarring), offering an immediate alternative to a liver biopsy.
B18: Measures liver fat content.
B19: Biomarker
B20: CAP score (dB/m)
B21: Typical ranges:
B22: S0: <248 dB/m
B23: S1: 248–267 dB/m
B24: S2: 268–279 dB/m
B25: S3: ≥280 dB/m
B26: Liver Stiffness Measurement (LSM) | C26: Liver Stiffness Measurement (LSM) is a quick, painless, and non-invasive test used to quantify the amount of scarring (fibrosis) or stiffness in the liver. It uses elastography technology (like FibroScan) to measure the speed of shear waves passing through the liver, producing results in kilopascals (kPa). How the Test Works? LSM applies a gentle vibration that sends a shear wave through the skin and into your liver tissue. The machine measures exactly how fast this wave travels the stiffer the liver, the faster the wave passes through. Healthy Liver: Soft and elastic, resulting in slower wave propagation and a lower kPa value (usually under 6–8 kPa). Damaged/Scared Liver: Stiff and hard, resulting in faster wave propagation and a higher kPa value. Interpreting the ResultsWhile exact cut-off ranges differ depending on the underlying cause of your liver disease (e.g., Hepatitis B/C, fatty liver disease), the results generally indicate the following: F0 - F1 (No to mild fibrosis): < 6.0 to 7.0 kPa. F2 (Moderate fibrosis): ~ 7.0 to 9.5 kPa. F3 (Severe fibrosis): ~ 10.0 to 14.0 kPa. F4 (Cirrhosis): Typically > 14.0 to 17.0 kPa. Why LSM is Used? Alternative to Biopsy: Replaces the need for painful surgical liver biopsies in many cases. Disease Monitoring: Helps track the progression of chronic conditions like NASH/MASLD, Hepatitis, and cirrhosis. Treatment Evaluation: Assesses how well the liver is healing following therapies
B27: Measures fibrosis.
B28: Biomarker
B29: Liver stiffness (kPa)
B30: Typical fibrosis stages:
B31: F0–F1: <7 kPa
B32: F2: 7–9.5 kPa
B33: F3: 9.5–12.5 kPa
B34: F4: >12.5 kPa
B35: 3. Magnetic Resonance Imaging (MRI) Biomarkers | C35: MRI biomarkers are measurable, quantitative characteristics derived from MRI scans that indicate normal biological processes, pathogenic changes, or responses to therapy. By analyzing parameters like tissue volume, blood flow, and diffusion, they provide objective data used for early disease detection, precise diagnosis, and treatment monitoring. Common types of MRI biomarkers include: Volumetric Biomarkers: Measure the size and volume of specific organs or tissues. For example, tracking regional brain atrophy (such as hippocampal shrinkage) is a vital structural biomarker in the assessment of Alzheimer's disease. Diffusion-Weighted Imaging (DWI) & Tractography: Track the microscopic movement of water molecules within tissues. Commonly used to detect early strokes, they are also effective biomarkers for evaluating tumors and neurodegenerative disorders like Parkinson's disease. Perfusion Biomarkers (DSC/DCE): Measure blood flow and the integrity of blood vessels in tissues. They help identify areas of active tumor growth or the penumbra (tissue at risk) during a stroke. Functional MRI (fMRI): Measures brain activity by detecting changes in blood oxygenation. Resting-state fMRI maps baseline neural networks, acting as a biomarker for cognitive and psychological disorders. Quantitative MRI (qMRI) & Mapping: Provide objective numerical metrics of underlying tissue properties (e.g., T1 and T2 relaxation times). These parametric maps are widely used for assessing muscle damage, liver iron overload, and brain microstructural changes.
B36: MRI-PDFF (Proton Density Fat Fraction) | C36: MRI-PDFF (Magnetic Resonance Imaging-Proton Density Fat Fraction) is a non-invasive, highly accurate imaging technique used to quantify the percentage of fat within tissues. Primarily used to measure liver fat, it acts as a precise alternative to liver biopsy for diagnosing and monitoring conditions like NAFLD (Nonalcoholic Fatty Liver Disease). The technique relies on advanced chemical-shift imaging to separate water and fat signals in the body. By doing so, it calculates the ratio of mobile protons in fat (triglycerides) to the total mobile protons in both fat and water. Clinical Value: Provides an objective, quantitative percentage of fat rather than a subjective visual estimate. Diagnosis & Monitoring: Normal liver fat is generally below \(5\%\) to \(6\%\). MRI-PDFF can categorize steatosis as mild (\(6\%-17\%\)), moderate (\(17\%-22\%\)), or severe (\(>22\%\)), and is highly effective at tracking whether fat is increasing or decreasing over time in response to diet, exercise, or medical therapies. Dual Capability: It can often generate \(R2^{*}\) maps simultaneously, allowing clinicians to measure liver iron concentration during the exact same scan. Research & Validation: Widely accepted as a primary biomarker in clinical trials and validated against biopsy and MR spectroscopy.
B37: Current gold-standard non-invasive biomarker for hepatic fat quantification.
B38: Biomarker
B39: MRI-PDFF (%)
B40: Interpretation:
B41: Normal: <5%
B42: Mild steatosis: 5–15%
B43: Moderate: 16–30%
B44: Severe: >30%
B45: Magnetic Resonance Spectroscopy (MRS) | C45: Magnetic Resonance Spectroscopy (MRS) is a non-invasive, radiation-free diagnostic test that measures biochemical and metabolic changes inside the body's tissues. While conventional MRI provides anatomical pictures, MRS acts as a "virtual biopsy" by charting specific metabolite concentrations (such as cellular turnover and neurotransmitter levels) on a graph. How MRS WorksMRS is performed on the same machine as a standard MRI using magnetic fields and radio waves. However, rather than mapping tissue based on water molecules, MRS translates radiofrequency signals into a spectrum of peaks. Each peak represents a specific chemical compound resonating at a distinct frequency, and the height of the peak corresponds to the concentration of that chemical. Clinical ApplicationsWhile MRS can be applied to the breast, prostate, or liver, it is most frequently used to evaluate brain. Common clinical uses include: Brain Tumors: It helps determine tumor type, aggressiveness, and can distinguish between a recurrent tumor and dead tissue caused by radiation (radiation necrosis). Neurological Disorders: It detects cellular or tissue changes associated with stroke, epilepsy, Alzheimer's, and multiple sclerosis. Pediatric Conditions: It aids in the identification of inborn errors of metabolism. Key Metabolites Measured Depending on the area being scanned, MRS identifies specific markers that indicate tissue health: N-acetyl aspartate (NAA): A marker of healthy neurons; typically reduced when tissue is damaged by disease or tumors. Choline: Represents cell membrane turnover; elevated levels often suggest rapid cell proliferation or cancer. Creatine: Indicates cellular energy; often used as a baseline internal reference because its levels remain relatively stable. Lactate: A byproduct of anaerobic metabolism; frequently spikes in aggressive tumors or after severe strokes.
B46: Highly accurate assessment of liver triglycerides.
B47: Biomarkers
B48: Hepatic lipid fraction
B49: Hepatic triglyceride content
B50: 4. Magnetic Resonance Elastography (MRE) | C50: Magnetic Resonance Elastography (MRE) is a non-invasive, advanced imaging technique that maps and measures the stiffness of internal body tissues. It acts as a digital form of physical palpation, allowing doctors to identify diseased, fibrotic, or cancerous tissues based on how elastic or hard they are. How it works? MRE works in three distinct phases: Wave Generation: A small pneumatic or acoustic device is placed on the patient's body (usually over the abdomen) to transmit low-frequency, harmless mechanical vibrations into the tissues. Imaging: A specialized MRI sequence is used to track the speed and propagation of these shear waves as they move through the organ. Because shear waves travel faster through stiff tissue than soft tissue, their velocity reveals the underlying structural health. Mapping: Specialized algorithms translate this data into quantitative, color-coded visual maps called elastograms, where softer areas appear in one color and stiffer, abnormal areas in another. Primary Clinical Applications Liver Fibrosis: MRE is most commonly used to detect, quantify, and stage liver fibrosis or cirrhosis caused by conditions like fatty liver disease or hepatitis. It is frequently utilized as a comfortable, whole-organ alternative to an invasive liver biopsy. Other Organs: While liver assessment is the standard use, MRE is also utilized for evaluating tissue stiffness in the brain, breast, prostate, spleen, and skeletal muscles. Key Advantages Compared to traditional imaging and biopsies, MRE offers a significant reduction in sampling errors because it images the entire organ rather than a tiny extracted piece of tissue. Additionally, it is often more reliable than ultrasound-based elastography for patients with high BMIs, as sound wave images can be distorted by body habitus
B51: Most accurate imaging biomarker for fibrosis.
B52: Biomarkers
B53: Liver stiffness (kPa)
B54: Shear wave velocity
B55: Approximate stages:
B56: F0–F1: <2.9 kPa
B57: F2: 2.9–3.6 kPa
B58: F3: 3.6–4.7 kPa
B59: F4: >4.7 kPa
B60: 5. Multiparametric MRI Biomarkers | C60: Multiparametric MRI (mpMRI) combines multiple specialized scanning techniques to extract both structural and functional tissue biomarkers. It evaluates organs non-invasively, providing detailed maps of cellularity, blood flow, and tissue composition without surgical biopsy. The three primary imaging biomarkers derived from an mp MRI include: 1. Diffusion-Weighted Imaging (DWI) What it measures: The random movement (Brownian motion) of water molecules within tissues. Clinical application: Highly cellular tissues (e.g., aggressive tumors or dense scar tissue) restrict water movement, creating a distinct signal known as restricted diffusion. It helps differentiate between benign and malignant lesions and is often quantified using Apparent Diffusion Coefficient (ADC) maps. 2. Dynamic Contrast-Enhanced (DCE) MRI What it measures: Tissue vascularity, capillary permeability, and blood flow. Clinical application: An intravenous contrast agent (usually gadolinium) is injected, and scans rapidly track how it enters and exits the tissue. Tumors often grow leaky, abnormal blood vessels, causing rapid contrast uptake and washout. This biomarker measures how quickly and densely blood perfuses the lesion. 3. T2-Weighted Imaging (T2WI) What it measures: The water content and structural anatomy of tissues. Clinical application: Provides a high-resolution, anatomical baseline map of the organ. It highlights structural abnormalities, such as zones of inflammation, fluid accumulation, or areas where normal tissue architecture has been disrupted. Additional Advanced Biomarkers Include: Magnetic Resonance Spectroscopy (MRS): Analyzes the chemical composition of a specific voxel of tissue to identify metabolites (e.g., choline, citrate) that indicate malignant metabolic activity. Proton Density Fat Fraction (PDFF): Quantifies the exact proportion of fat within tissue, commonly used in liver and metabolic diseases. Blood Oxygen Level-Dependent (BOLD) MRI: Assesses tissue oxygenation and hypoxia, which are strong indicators of tumor aggressiveness and resistance to therapies.
B61: Corrected T1 (cT1) | C61: Corrected T1 (cT1) is a specialized, non-invasive MRI biomarker used to assess and monitor liver diseases like MASH (metabolic dysfunction-associated steatohepatitis). It serves as a surrogate proxy for hepatic inflammation and fibrosis by correcting conventional MRI T₁ mapping for the confounding effects of excess liver iron. Key Characteristics of cT1Mechanism: Measures the amount of extracellular fluid in liver tissue, which increases during inflammation and fibrosis. Iron Correction: Conventional T₁ values can be artificially lowered by iron accumulation. The "corrected" (cT1) measure ensures accurate, standardized readings across all major MRI scanner platforms. Clinical Utility: cT1 acts as a highly effective pre-screening and diagnostic tool to limit the need for painful, invasive liver biopsies. It is also valuable for identifying patients at the highest risk of disease progression. Reference Ranges: In healthy, low-risk populations, normal cT1 values range from roughly 573 to 852 ms (with a median of 666 ms). Values consistently above 875 ms are strong predictors of serious, liver-related clinical events and mortality. Why cT1 MattersCurrently? The standard of care for liver assessment relies heavily on biopsies or elastography. However, recent clinical and economic analyses show that MRI cT1 is a cost-effective, non-invasive alternative. It is increasingly being adopted to guide clinical decisions, such as prescribing and monitoring responses to FDA-approved therapies like resmetirom.
B62: Reflects:
B63: Inflammation
B64: Fibrosis
B65: Ballooning injury
B66: Biomarker
B67: cT1 value (ms)
B68: T2 Mapping | C68: T2 mapping is an advanced MRI technique that calculates and maps the transverse relaxation time (T2) of tissues. By creating a parametric image (map) where each pixel's color corresponds to a specific T2 value, it provides a quantitative measure of tissue health, making it highly sensitive to changes in water content, inflammation, or structural degradation. How it Works? When exposed to a magnetic field, protons in tissues are pushed out of alignment. As they realign and lose phase coherence, they emit a signal known as T2 decay. T2 mapping measures this decay across multiple echo times, generating an absolute numerical value (typically in milliseconds) for each region of the tissue. Higher water content or tissue damage usually results in longer T2 relaxation times. Common Clinical Applications Cardiology: It is a cornerstone of cardiovascular magnetic resonance (CMR) for detecting myocardial edema, inflammation, and ischemia without requiring contrast agents. It is used to diagnose conditions like acute myocarditis, heart transplant rejection, and myocardial infarction. Musculoskeletal (MSK): It acts as a highly sensitive biomarker for the early detection of cartilage degeneration (e.g., in the knee), often revealing structural breakdown before physical or morphological changes can be seen on standard scans. Neurology: Specialized multi-echo T2 mapping can isolate water trapped within the myelin sheath (Myelin Water Fraction), making it a valuable tool for tracking conditions like multiple sclerosis. Advantages Unlike traditional, visually-weighted MRI scans which rely on subjective comparisons between healthy and unhealthy tissue T2 mapping provides objective, reproducible numbers. This allows physicians to easily track disease progression, monitor the success of ongoing treatments (such as chelation therapy), and compare patient data across different scanners and imaging centers
B69: Measures:
B70: Inflammation
B71: Edema
B72: T1 Relaxation Time | C72: T1 relaxation time (spin-lattice or longitudinal relaxation time) is a physical constant measuring how quickly an excited quantum system or nuclear spin returns to its resting ground state. In fields like MRI and spectroscopy, it defines the time required for net magnetization to recover to roughly 63% of its original equilibrium value. Key Concepts Mechanism: It involves the exchange of energy between excited spins and their surrounding environment (the "lattice"). As the absorbed energy is released as heat, spins realign with the main magnetic field. Mathematical Curve: The recovery process is exponential, modeled by the equation \(M(t) = M_{0}(1 - e^{\frac{-t}{T1}})\), where M(t) is the magnetization at time t, and M₀ is the maximum equilibrium magnetization. T1 in MRI: T1 times vary significantly depending on tissue composition (e.g., fat recovers its magnetization much faster than water-based fluids). These differences form the foundational contrast mechanism in T1-weighted MRI scans. T1 in Quantum Computing: In quantum systems (such as superconducting qubits), T1 (energy relaxation time) indicates how long a qubit in an excited state (\(\vert{}1\rangle\)) can maintain its state before it decays into the ground state (\(\vert{}0\rangle\)) through interactions with its environment.
B73: Measures:
B74: Fibrosis burden
B75: Inflammation
B76: Extracellular Volume Fraction (ECV) | C76: Extracellular Volume Fraction (ECV) is an advanced imaging biomarker that measures the percentage of tissue space outside of the cells. In cardiology, measuring myocardial ECV often using Cardiac Magnetic Resonance (CMR) Imaging is the gold standard for non-invasively detecting and quantifying conditions like diffuse fibrosis, heart muscle scarring, and amyloidosis. How ECV Works? The heart muscle is composed of cells (cardiomyocytes) and the extracellular matrix (the space and structural proteins surrounding the cells). When an imaging contrast agent (such as a gadolinium-based dye in an MRI) is injected, it circulates in the blood and collects in the extracellular space but does not enter healthy cells. By comparing the concentration of the contrast agent in the blood to its concentration in the heart muscle tissue, radiologists and cardiologists can calculate the precise percentage of that tissue that is "empty" space. Normal Range: A healthy myocardial ECV generally ranges between 25% and 30%. Elevated ECV: If the tissue becomes damaged, scarred, or infiltrated by abnormal proteins (like in amyloidosis), the extracellular matrix expands. This allows more contrast agent to gather, which drives the ECV percentage higher. Clinical Importance Doctors rely on ECV measurements as an objective indicator of heart disease severity and prognosis. An elevated ECV can point to: Myocardial Fibrosis: Stiffening or scarring of the heart muscle, which impairs the heart's ability to relax and pump effectively. Cardiac Amyloidosis: The buildup of abnormal proteins in the heart tissue, which increases the extracellular space significantly. Myocarditis or Edema: Inflammation or fluid buildup in the heart tissue, also expanding the extracellular space
B77: Measures:
B78: Fibrotic expansion
B79: 6. CT-Based Biomarkers | C79: CT-based biomarkers are objective, measurable features extracted from computed tomography (CT) scans using advanced analysis or artificial intelligence (AI). They go beyond traditional visual reading to provide quantifiable data on disease presence, progression, and patient risk without requiring invasive procedures. These biomarkers play a transformative role across several major medical specialties: Cardiovascular Health: CT scans can opportunistically measure aortic valve calcification, visceral fat, and plaque burden. These AI-driven measurements have been shown to outperform traditional tools like the Framingham Risk Score in predicting major adverse events like heart attacks or strokes. Oncology & Immunotherapy: AI and radiomics (the extraction of quantitative features from medical images) are used to analyze tumor size, shape, and texture. Deep learning algorithms can now generate scores from pretreatment CTs to predict a patient's response to immunotherapies (like PD-L1 inhibitors), often independently of standard biopsy markers. Biological Aging & Chronic Disease: Body composition CT biomarkers evaluate bone mineral density, muscle mass (sarcopenia), and liver or abdominal fat. When combined, these tissue-level metrics act as a measure of "biological age," which is highly predictive of long-term longevity and the risk of chronic conditions like hypertension or chronic kidney disease. Pulmonology: In lung diseases like COPD, CT-based metrics such as Parametric Response Mapping (PRM) allow for the voxel-by-voxel mapping of lung tissue to differentiate between airway disease and emphysema. Neurology: In acute settings, quantitative CT biomarkers such as hematoma density, midline shift, and regional attenuation offer early, objective predictions of patient mortality and neurological outcomes.
B80: Liver Attenuation Index (LAI) | C80: The Liver Attenuation Index (LAI) is a non-invasive CT scan metric used to quantify hepatic steatosis (fatty liver). Calculated as the difference in density between the liver and the spleen (LAI = Liver HU − Spleen HU), a normal index is generally greater than +5. Lower scores indicate higher fat content.Clinical InterpretationThe LAI is primarily used during pre-transplant evaluations (such as in living liver donors) to estimate the percentage of macrovesicular steatosis without needing an invasive biopsy. Standard LAI thresholds on non-contrast CT scans typically correlate as follows: > +5: Normal liver (typically 0-10% fat) 0 to +5: Mild steatosis (10-30% fat) < 0: Severe steatosis (>30% fat) How It Is Measured? To find the LAI, a radiologist evaluates non-contrast CT images by placing a circular Region of Interest (ROI) over several areas of the liver and the spleen to measure their tissue density in Hounsfield Units (HU). In a healthy individual, the liver normally measures between 50 and 60 HU, which is about 10 HU higher than the spleen. As fat accumulates in the liver, its attenuation (density) drops, decreasing the LAI. LimitationsWhile it is an excellent tool for ruling out donors with high levels of fat, the LAI can sometimes be inaccurate. Factors such as iron or copper overload, glycogen accumulation, and local inflammation can increase liver density, potentially hiding underlying fatty changes. Because of these limitations, many medical centers are now relying on MRI-derived Proton Density Fat Fraction (PDFF) as a more reliable and less confounded method for fat quantification.
B81: Biomarkers
B82: Liver attenuation (HU)
B83: Liver-to-spleen attenuation ratio
B84: Features:
B85: Reduced attenuation indicates steatosis
B86: CT Fat Fraction | C86: A CT fat fraction is an imaging metric that measures the percentage of lipid (fat) volume within an organ most commonly the liver. It quantifies how much fat has accumulated in tissues, helping radiologists and doctors diagnose and monitor conditions like hepatic steatosis (fatty liver disease). How It Works and What It Measures? The Metric: It represents the proportion of fat compared to the total tissue volume (or the ratio of fat signals to fat plus water signals). Normal vs. Abnormal: A fat fraction of less than 5% is generally considered normal. Anything above that indicates some degree of steatosis, which can be further graded depending on the severity. Methods of MeasurementUnenhanced (Non-contrast) CT: Traditional, non-contrast CT scans calculate the fat fraction by measuring X-ray attenuation in Hounsfield Units (HU). Fat has a much lower density than normal tissue or water, so as liver fat increases, the HU value drops. Advanced CT Techniques: Standard CT scans can sometimes miss mild fatty liver or be affected by contrast agents. Newer technologies like Dual-Energy CT (DECT) and Photon-Counting CT (PCCT) perform "material decomposition" to directly calculate fat fractions. These methods offer an accuracy that closely rivals MRI. Clinical Significance: Quantifying the CT fat fraction is essential for assessing conditions like MAFLD (Metabolic Dysfunction-Associated Steatotic Liver Disease). Measuring the exact percentage allows clinicians to determine how severe the fat accumulation is and track whether lifestyle changes or medical treatments are reducing the fat levels in the organ.
B87: Biomarker
B88: Hepatic fat percentage
B89: 7. Shear Wave Elastography (SWE) | C89: Shear Wave Elastography (SWE) is a non-invasive, ultrasound-based imaging technique that maps and measures the stiffness of soft tissues. By applying targeted acoustic pulses to generate and track tiny "shear waves" inside the body, SWE provides an objective, real-time assessment of tissue elasticity. How It Works? Wave Generation: An ultrasound probe sends a focused pulse into the tissue, generating transient "shear waves" that travel perpendicular to the primary ultrasound beam. Velocity Tracking: The imaging system tracks how fast these waves move. Shear waves travel faster through stiff, dense tissue and slower through softer, elastic tissue. Quantification: The machine calculates the tissue's stiffness (usually in kilopascals, or kPa) and maps it as a color-coded overlay on a standard anatomical ultrasound. Common Clinical Applications SWE is typically used as a follow-up or diagnostic adjunct to standard ultrasound to help clinicians evaluate and stage various medical conditions: Liver: Used to stage liver fibrosis and detect cirrhosis or fatty liver disease without requiring a biopsy. Breast & Thyroid: Helps differentiate between benign and malignant masses, as cancers are generally much stiffer than normal tissue or benign lesions. Musculoskeletal System: Evaluates tissue changes in muscles, tendons, ligaments, and nerves.
B90: Point Shear Wave Elastography (pSWE) | C90: Point Shear Wave Elastography (pSWE) is an ultrasound technique that measures tissue stiffness. By using an acoustic push pulse to generate shear waves, the system calculates wave velocity within a localized region. Stiffer tissue indicates faster wave propagation, making it highly effective for non-invasively assessing conditions like liver fibrosis.Unlike older blind-vibration techniques (such as Transient Elastography/FibroScan), pSWE is integrated directly into standard ultrasound machines. This allows clinicians to use real-time B-mode imaging to guide their measurements, avoiding obstructions like blood vessels, ribs, and bile ducts. Key Characteristics and Uses Quantitative Data: It provides exact, objective measurements of tissue elasticity, often reducing the need for invasive biopsies. Image Guidance: The targeted Region of Interest (ROI) ensures that off-target tissue is not mistakenly measured. Primary Applications: While primarily used in hepatology to stage chronic liver disease and cirrhosis, it is also applied to evaluate thyroid nodules, breast lesions, and musculoskeletal tissues
B91: Biomarkers
B92: Shear wave velocity (m/s)
B93: Liver stiffness (kPa)
B94: Two-Dimensional SWE | C94: Two-Dimensional Shear Wave Elastography (2D-SWE) is an advanced medical ultrasound technology that non-invasively measures the stiffness of biological tissues. By tracking the propagation of shear waves generated within the body, it creates a real-time, color-coded 2D map that quantitatively displays tissue elasticity in kilopascals (kPa). How It Works? Acoustic Radiation: The ultrasound probe emits a brief, focused push pulse into the tissue, which generates microscopic shear waves. Speed vs. Stiffness: The machine tracks how fast these waves travel. Because shear waves move faster in stiffer tissues, their speed directly correlates to the tissue's elasticity. Real-Time Visualization: Unlike older techniques (like transient elastography) that only provide a single-point measurement without anatomical imaging, 2D-SWE produces a vivid, 2D visual mapping overlaid on a standard grayscale B-mode scan. Primary Clinical Uses Liver Fibrosis: It is primarily used to stage and monitor liver fibrosis and cirrhosis, serving as a non-invasive alternative to liver biopsies. Lesion Characterization: Doctors use it to distinguish between benign and malignant masses in organs like the breast and thyroid. Other Applications: It is also used to evaluate muscle stiffness (e.g., in chronic obstructive pulmonary disease or compartment syndrome) and pancreatic health
B95: Biomarkers
B96: Mean liver stiffness
B97: Elasticity maps
B98: 8. Contrast-Enhanced Imaging Biomarkers | C98: Contrast-Enhanced Imaging Biomarkers (CEIBs) are quantitative or qualitative metrics derived from medical images that are taken after the administration of a contrast agent. They measure tissue perfusion, blood volume, and capillary permeability providing noninvasive, biological insights into microvascular function and cellular composition. These biomarkers are essential for clinical practice, primarily in oncology, cardiology, and neurology, and operate through a few key frameworks: 1. How They Work CEIBs are generated using imaging technologies like Dynamic Contrast-Enhanced MRI (DCE-MRI), CT perfusion, or Contrast-Enhanced Ultrasound (CEUS). A contrast agent (such as a gadolinium-based compound for MRI or an iodine-based agent for CT) is injected into the bloodstream. As the agent moves through the microvasculature and leaks into the surrounding tissue, the imaging system tracks the signal changes over time. 2. Common Clinical Parameters Mathematical algorithms and compartmental pharmacokinetic models (like the Tofts model) convert these temporal signal changes into measurable biological metrics. Key CEIB parameters include: \(K^{trans}\) (Transfer Constant): Measures the rate of contrast agent transfer between blood plasma and the extracellular space, reflecting capillary permeability and blood flow. \(v_{p}\) (Plasma Volume Fraction): Quantifies the volume of blood within a specific tissue region. \(v_{e}\) (Extracellular Space Volume Fraction): Measures the volume of the space outside the cells where the contrast agent accumulates. 3. Key Applications Oncology: Tumor angiogenesis (the growth of new, leaky blood vessels) leads to distinct contrast enhancement patterns. CEIBs are used to characterize tumor aggressiveness, guide biopsies, and monitor early responses to antiangiogenic and chemotherapy treatments. Neurology: CEIBs help evaluate blood-brain barrier disruptions, which are indicative of conditions like strokes, multiple sclerosis, or metastatic brain tumors. Cardiology: They are utilized to assess myocardial perfusion (blood flow to the heart muscle) and capillary integrity.
B99: Contrast-Enhanced Ultrasound (CEUS) | C99: Contrast-Enhanced Ultrasound (CEUS) is a real-time imaging technique that uses intravenous gas-filled microbubbles to significantly improve the clarity of traditional ultrasound scans. It is primarily used to assess organ blood flow, track vascular patterns, and identify or characterize tumors without exposing the patient to ionizing radiation. How It Works? The Microbubbles: The contrast agent consists of tiny, biocompatible gas microbubbles (similar in size to red blood cells) encased in a lipid, protein, or polymer shell. Resonance: When ultrasound sound waves hit these microbubbles, they vibrate and resonate. This produces a strong, nonlinear harmonic echo that traditional machines can detect, lighting up the vessels while the surrounding background tissue appears dark. Intravascular Tracking: Unlike contrast agents used in CT scans or MRIs, the microbubbles in CEUS remain strictly within the bloodstream and do not leak into the surrounding tissues. Key Clinical Advantages Safety Profile: Because the microbubbles are exhaled naturally through the lungs, they pose zero risk of nephrotoxicity (kidney damage) or hepatotoxicity. This makes CEUS an excellent alternative for patients with renal failure or severe allergies to iodine/gadolinium. Real-Time Dynamic Imaging: It allows physicians to watch the blood flow into and out of an organ or lesion in real time, making it easier to distinguish between benign and malignant growths. Radiation-Free: It is a non-invasive, radiation-free procedure that can often be performed bedside.Primary ApplicationsLiver & Kidneys: Widely used to detect, characterize, and stage focal liver lesions (like hepatocellular carcinoma or hemangiomas) and small renal masses. Vascular & Heart: Utilized to evaluate myocardial perfusion, diagnose heart disease, and monitor the risk of stroke. Prostate & Breast: Helps guide targeted biopsies and monitor the effectiveness of various cancer therapies.Comparison to Other Modalities Compared to CT/MRI: CEUS relies purely on blood flow timing without relying on radiation or potentially harmful dyes. However, it is highly operator-dependent, does not offer cross-sectional views, and may be limited by the patient's body habitus (e.g., deep organs are sometimes hard to image clearly).
B100: Biomarkers
...

Sheet Classification
A1: 1. Established Clinical Biomarkers for NAFLD/NASH
A2: These are commonly used in diagnosis, disease assessment, or fibrosis evaluation:
A3: Biomarker | B3: Role in NAFLD/NASH
A4: ALT | B4: Hepatocellular injury
A5: AST | B5: Liver injury and fibrosis
A6: GGT | B6: Liver dysfunction
A7: Total Bilirubin | B7: Liver function
A8: Total Cholesterol | B8: Metabolic syndrome marker
A9: Triglycerides (TG) | B9: Hepatic steatosis
A10: Fasting Blood Glucose | B10: Insulin resistance
A11: Fasting Glucose | B11: Metabolic dysfunction
A12: Insulin Resistance | B12: Central mechanism of NAFLD
A13: HOMA-IR | B13: Insulin resistance assessment
A14: Alpha-fetoprotein (AFP) | B14: Advanced liver disease/HCC surveillance
... A21: CRP | B21: Systemic inflammation
A22: 2. Inflammatory and Immune Biomarkers Associated with NAFLD
A23: Biomarker | B23: Significance
A24: IL6 | B24: Promotes hepatic inflammation
A25: IL6R | B25: IL-6 signaling
A26: TNF | B26: Key inflammatory cytokine
A27: IL1A | B27: Pro-inflammatory cytokine
A28: ICAM-1 | B28: Endothelial activation and inflammation
A29: P-selectin | B29: Inflammation and vascular dysfunction
A30: Fas | B30: Hepatocyte apoptosis
A31: NFKBIB | B31: NF-κB signaling pathway
A32: LEPR | B32: Obesity and metabolic regulation
A33: 3. Genetic Susceptibility Biomarkers
A34: These are associated with NAFLD risk and progression rather than routine diagnosis:
A35: Gene | B35: Importance
A36: PNPLA3 | B36: Strongest genetic risk factor for NAFLD/NASH
A37: PPP1R3B | B37: Hepatic glycogen and lipid metabolism
A38: HNF1A | B38: Glucose and lipid metabolism
A39: HNF4A | B39: Hepatic differentiation and lipid metabolism
A40: RORA | B40: Lipid metabolism and circadian regulation
A41: 4. Emerging/Research Biomarkers from GWAS, Transcriptomics, or Proteomics
A42: These have been reported in omics studies but are not validated clinical biomarkers:
A43: Marker
A44: GBGT1
A45: IL1F10
A46: LNK (SH2B3)
A47: Poly(A) binding protein
A48: PABPC4
A49: PSMG1
A50: RGS6
A51: SALL1
A52: ASCL1
... A99: ABO
